{
    "BuildID": "91120da1-d0e1-4e63-b6be-8f5bc27a5c43",
    "Command": "project:deploy",
    "ProjectID": "6c12a4f49c2e1c74dbc0beaf340cbc67",
    "ProjectStateHash": "bf94e0e38057bb36cc076a3517c9fbcf2236a53e630fac70aad28319d237067a",
    "StageCompletedAt": 3,
    "EarliestFatalError": 0,
    "StartTime": 1742912713840,
    "EndTime": 1742912841578,
    "PlaygroundUserID": 21453,
    "OperatingSystem": "win32",
    "UnityPackageID": null,
    "TargetPlatform": "playground",
    "UnityVersion": "2022.3.7f1",
    "LunaVersion": "6.2.1",
    "LogCount": 15,
    "Logs": [
        {
            "LogID": "320be4b9-5f23-464d-81aa-5069f967d330",
            "Order": 10,
            "Timestamp": 1742912842179,
            "Stage": 3,
            "ErrorType": 0,
            "ErrorCode": "LP3005",
            "Description": "You are using a Luna reserved keyword: Handle",
            "Details": [
                "You are using a reserved keyword: Handle for Luna. Please change the name of the field/class"
            ],
            "DescriptionValues": [
                "Handle"
            ],
            "DetailsValues": [
                "Handle"
            ],
            "LogCount": 1,
            "LinePosition": 35,
            "FilePath": "D:\\UnityPri\\My project\\Assets\\Scenes\\Assets\\Joystick Pack\\Scripts\\Base\\Joystick.cs",
            "ClassName": "",
            "MemberName": "",
            "Severity": 0
        },
        {
            "LogID": "1e1a1139-2440-4b8d-a43f-0978b65ab50f",
            "Order": 10,
            "Timestamp": 1742912842181,
            "Stage": 3,
            "ErrorType": 0,
            "ErrorCode": "LP3005",
            "Description": "You are using a Luna reserved keyword: handle",
            "Details": [
                "You are using a reserved keyword: handle for Luna. Please change the name of the field/class"
            ],
            "DescriptionValues": [
                "handle"
            ],
            "DetailsValues": [
                "handle"
            ],
            "LogCount": 1,
            "LinePosition": 35,
            "FilePath": "D:\\UnityPri\\My project\\Assets\\Scenes\\Assets\\Joystick Pack\\Scripts\\Base\\Joystick.cs",
            "ClassName": "",
            "MemberName": "",
            "Severity": 0
        },
        {
            "LogID": "fdd288c2-964d-404d-98c0-200c1863b47d",
            "Order": 10,
            "Timestamp": 1742912842656,
            "Stage": 3,
            "ErrorType": 1,
            "ErrorCode": "LP3006",
            "Description": "You are not using the Luna API: Playable.InstallFullGame",
            "Details": [
                "You are not using the Luna API: Playable.InstallFullGame. Some ad networks require these calls. Please add these calls to ensure your playable works on all ad networks. Check documentation for more information."
            ],
            "DescriptionValues": [
                "Playable",
                "InstallFullGame"
            ],
            "DetailsValues": [
                "Playable",
                "InstallFullGame"
            ],
            "LogCount": 1,
            "LinePosition": null,
            "FilePath": "",
            "ClassName": "",
            "MemberName": "",
            "Severity": 0
        },
        {
            "LogID": "2d48665a-ba70-48ab-8dc3-84002d3d1159",
            "Order": 10,
            "Timestamp": 1742912842658,
            "Stage": 3,
            "ErrorType": 1,
            "ErrorCode": "LP3006",
            "Description": "You are not using the Luna API: LifeCycle.GameEnded",
            "Details": [
                "You are not using the Luna API: LifeCycle.GameEnded. Some ad networks require these calls. Please add these calls to ensure your playable works on all ad networks. Check documentation for more information."
            ],
            "DescriptionValues": [
                "LifeCycle",
                "GameEnded"
            ],
            "DetailsValues": [
                "LifeCycle",
                "GameEnded"
            ],
            "LogCount": 1,
            "LinePosition": null,
            "FilePath": "",
            "ClassName": "",
            "MemberName": "",
            "Severity": 0
        },
        {
            "LogID": "a7f9f42b-c9ff-4de9-978d-f462940dabd2",
            "Order": 10,
            "Timestamp": 1742912842659,
            "Stage": 3,
            "ErrorType": 3,
            "ErrorCode": "LP3007",
            "Description": "You are not using any custom events",
            "Details": [
                "You are not using any custom events. It is recommended to use custom events to have a better understanding of the playable."
            ],
            "DescriptionValues": [
                ""
            ],
            "DetailsValues": [
                ""
            ],
            "LogCount": 1,
            "LinePosition": null,
            "FilePath": "",
            "ClassName": "",
            "MemberName": "",
            "Severity": 0
        },
        {
            "LogID": "d2579e36-1c04-4bef-9ef0-4f4a302a4d20",
            "Order": 10,
            "Timestamp": 1742912842661,
            "Stage": 3,
            "ErrorType": 3,
            "ErrorCode": "LP3011",
            "Description": "You are not using any LunaPlaygroundFields attributes.",
            "Details": [
                "You are not using any LunaPlaygroundFields attributes, it allows you to configure your playable to different concepts to find the best variation, which can drastically improve playable performance on all ad networks."
            ],
            "DescriptionValues": null,
            "DetailsValues": null,
            "LogCount": 1,
            "LinePosition": null,
            "FilePath": "",
            "ClassName": "",
            "MemberName": "",
            "Severity": 0
        },
        {
            "LogID": "37bc82b5-5c0b-4f98-80b2-f7695bc308f6",
            "Order": 0,
            "Timestamp": 1742912765191,
            "Stage": 1,
            "ErrorType": 2,
            "ErrorCode": "LP1016",
            "Description": "Extensive usage of ParticleSystem Component",
            "Details": [
                "There is extensive usage of the ParticleSystem component.\nExcessive usage of any component can be detrimental to performance on lower and in some cases higher end devices, consider reducing the amount the component is used.\nRecommended count: 10, current count 48."
            ],
            "DescriptionValues": [
                "ParticleSystem"
            ],
            "DetailsValues": [
                "ParticleSystem",
                "10",
                "48"
            ],
            "LogCount": 1,
            "LinePosition": 0,
            "FilePath": "",
            "ClassName": "",
            "MemberName": "",
            "Severity": 0
        },
        {
            "LogID": "598d0503-8ee1-4e2c-9b8d-b93f310db6ec",
            "Order": 1,
            "Timestamp": 1742912765192,
            "Stage": 1,
            "ErrorType": 2,
            "ErrorCode": "LP1022",
            "Description": "Extensive use of shader variants",
            "Details": [
                "Extensive usage of shader variants negatively affects playable startup time. Please consider them to be less than 20 (38 found). Check Runtime analysis -> shader tab to see used shaders."
            ],
            "DescriptionValues": [],
            "DetailsValues": [
                "20",
                "38"
            ],
            "LogCount": 1,
            "LinePosition": 0,
            "FilePath": "",
            "ClassName": "",
            "MemberName": "",
            "Severity": 0
        },
        {
            "LogID": "04e1844f-ac41-4d41-ba90-21a0815705bc",
            "Order": 2,
            "Timestamp": 1742912765193,
            "Stage": 1,
            "ErrorType": 1,
            "ErrorCode": "LP1023",
            "Description": "Too many files for facebook platform",
            "Details": [
                "Too many files for facebook platform in use ($114) only $100 available"
            ],
            "DescriptionValues": [],
            "DetailsValues": [
                "114",
                "100"
            ],
            "LogCount": 1,
            "LinePosition": 0,
            "FilePath": "",
            "ClassName": "",
            "MemberName": "",
            "Severity": 0
        },
        {
            "LogID": "8e6fb824-4d1a-4520-879c-878788028a60",
            "Order": 3,
            "Timestamp": 1742912765250,
            "Stage": 1,
            "ErrorType": 0,
            "ErrorCode": "LP1027",
            "Description": "This DOTween version is not supported",
            "Details": [
                "The incorrect DOTween version for this Unity version is in use, please update or downgrade to the recommended version {0} in the package manager. Go to Window → Package Manager."
            ],
            "DescriptionValues": [],
            "DetailsValues": [
                ""
            ],
            "LogCount": 1,
            "LinePosition": 0,
            "FilePath": "",
            "ClassName": "",
            "MemberName": "",
            "Severity": 0
        },
        {
            "LogID": "15b10d5e-aca1-45a6-9058-2c1f2b89443d",
            "Order": 4,
            "Timestamp": 1742912765250,
            "Stage": 1,
            "ErrorType": 0,
            "ErrorCode": "LP1026",
            "Description": "This Cinemachine version is not supported",
            "Details": [
                "The incorrect Cinemachine version for this Unity version is in use, please update or downgrade to the recommended version {0} in the package manager. Go to Window → Package Manager."
            ],
            "DescriptionValues": [],
            "DetailsValues": [
                ""
            ],
            "LogCount": 1,
            "LinePosition": 0,
            "FilePath": "",
            "ClassName": "",
            "MemberName": "",
            "Severity": 0
        },
        {
            "LogID": "8913d470-363f-4ec2-a81d-2e867ca43a48",
            "Order": 5,
            "Timestamp": 1742912765250,
            "Stage": 1,
            "ErrorType": 0,
            "ErrorCode": "LP1015",
            "Description": "This TMP version is not fully supported",
            "Details": [
                "The incorrect Text Mesh Pro for this Unity version is in use, please update or downgrade to the recommended version {0} in the package manager. Go to Window → Package Manager"
            ],
            "DescriptionValues": [],
            "DetailsValues": [
                ""
            ],
            "LogCount": 1,
            "LinePosition": 0,
            "FilePath": "",
            "ClassName": "",
            "MemberName": "",
            "Severity": 0
        },
        {
            "LogID": "44991128-78b4-4e8f-951c-81f94628ee88",
            "Order": 6,
            "Timestamp": 1742912765251,
            "Stage": 1,
            "ErrorType": 0,
            "ErrorCode": "LP1032",
            "Description": "Package(s) is not supported in Luna",
            "Details": [
                "Currently package(s) com.unity.timeline are not supported in Luna. We recommend you to remove it and workaround it's functionality."
            ],
            "DescriptionValues": [
                "com.unity.timeline (1.7.5)"
            ],
            "DetailsValues": [
                "com.unity.timeline"
            ],
            "LogCount": 1,
            "LinePosition": 0,
            "FilePath": "D:/UnityPri/My project/Packages\\manifest.json",
            "ClassName": "",
            "MemberName": "",
            "Severity": 0
        },
        {
            "LogID": "4cdd8579-51b3-4452-a628-6ce067765dab",
            "Order": 7,
            "Timestamp": 1742912765253,
            "Stage": 1,
            "ErrorType": 2,
            "ErrorCode": "LP1010",
            "Description": "Looks like a collider was scaled, this might affect performance.",
            "Details": [
                "TankPrefab",
                "SM_Wep_Mortar_Shell_01 (1) Variant",
                "SM_Wep_Mortar_Shell_01 (1) Variant 1",
                "ground",
                "ground",
                "ground",
                "generic_cliff"
            ],
            "DescriptionValues": [],
            "DetailsValues": [],
            "LogCount": 7,
            "LinePosition": 0,
            "FilePath": "",
            "ClassName": "",
            "MemberName": "",
            "Severity": 0
        },
        {
            "LogID": "c28316ae-0e7e-496f-ac7c-198f94f11e5c",
            "Order": 8,
            "Timestamp": 1742912765253,
            "Stage": 1,
            "ErrorType": 3,
            "ErrorCode": "LP1008",
            "Description": "There are missing components on Text (TMP).",
            "Details": [
                "Text (TMP)",
                "Text (TMP)"
            ],
            "DescriptionValues": [
                "Text (TMP)"
            ],
            "DetailsValues": [],
            "LogCount": 2,
            "LinePosition": 0,
            "FilePath": "",
            "ClassName": "",
            "MemberName": "",
            "Severity": 0
        }
    ]
}