{"id":31588,"path":"Assets\/Scenes\/Assets\/Prefabs\/howitzer.fbx","assetBundleId":-1,"components":[{"type":7,"id":31642,"data":[0,0,0,1,1,1,-3.7748947079308E-08,0,0,1]}],"children":[{"id":33854,"path":"Assets\/Scenes\/Assets\/Prefabs\/howitzer.fbx","assetBundleId":-1,"components":[{"type":7,"id":33268,"data":[0,0,0,1,1,1,0,0,0,1]},{"type":11,"id":34300,"data":[12,34814]},{"type":13,"id":32044,"data":[null,null,1,14,34856,[14,34856],1,1,0,0,-1,-1,1,1,0,0,1,1]}],"children":[],"data":["pCylinder1",0,1,0,0]},{"id":32548,"path":"Assets\/Scenes\/Assets\/Prefabs\/howitzer.fbx","assetBundleId":-1,"components":[{"type":7,"id":33270,"data":[0,0,0,1,1,1,0,0,0,1]},{"type":11,"id":34000,"data":[12,34932]},{"type":13,"id":31788,"data":[null,null,1,14,32128,[14,32128],1,1,0,0,-1,-1,1,1,0,0,1,1]}],"children":[],"data":["pCylinder4",0,1,0,0]},{"id":32550,"path":"Assets\/Scenes\/Assets\/Prefabs\/howitzer.fbx","assetBundleId":-1,"components":[{"type":7,"id":33272,"data":[0,0,0,1,1,1,0,0,0,1]},{"type":11,"id":33942,"data":[12,34728]},{"type":13,"id":32130,"data":[null,null,1,14,31624,[14,31624],1,1,0,0,-1,-1,1,1,0,0,1,1]}],"children":[],"data":["pCylinder5",0,1,0,0]},{"id":32552,"path":"Assets\/Scenes\/Assets\/Prefabs\/howitzer.fbx","assetBundleId":-1,"components":[{"type":7,"id":33274,"data":[0,0,0,1,1,1,0,0,0,1]},{"type":11,"id":34456,"data":[12,34806]},{"type":13,"id":32138,"data":[null,null,1,14,31700,[14,31700],1,1,0,0,-1,-1,1,1,0,0,1,1]}],"children":[],"data":["pCylinder6",0,1,0,0]},{"id":33878,"path":"Assets\/Scenes\/Assets\/Prefabs\/howitzer.fbx","assetBundleId":-1,"components":[{"type":7,"id":33276,"data":[0,0,0,1,1,1,0,0,0,1]},{"type":11,"id":34250,"data":[12,34648]},{"type":13,"id":31850,"data":[null,null,1,14,31700,[14,31700],1,1,0,0,-1,-1,1,1,0,0,1,1]}],"children":[],"data":["pCylinder7",0,1,0,0]},{"id":32554,"path":"Assets\/Scenes\/Assets\/Prefabs\/howitzer.fbx","assetBundleId":-1,"components":[{"type":7,"id":33278,"data":[0,0,0,1,1,1,0,0,0,1]},{"type":11,"id":34086,"data":[12,34830]},{"type":13,"id":32062,"data":[null,null,1,14,31700,[14,31700],1,1,0,0,-1,-1,1,1,0,0,1,1]}],"children":[],"data":["pCylinder8",0,1,0,0]},{"id":32556,"path":"Assets\/Scenes\/Assets\/Prefabs\/howitzer.fbx","assetBundleId":-1,"components":[{"type":7,"id":33280,"data":[0,0,0,1,1,1,0,0,0,1]},{"type":11,"id":34154,"data":[12,34816]},{"type":13,"id":32048,"data":[null,null,1,14,31624,[14,31624],1,1,0,0,-1,-1,1,1,0,0,1,1]}],"children":[],"data":["pCylinder14",0,1,0,0]},{"id":32558,"path":"Assets\/Scenes\/Assets\/Prefabs\/howitzer.fbx","assetBundleId":-1,"components":[{"type":7,"id":33282,"data":[0,0,0,1,1,1,0,0,0,1]},{"type":11,"id":33990,"data":[12,34634]},{"type":13,"id":31838,"data":[null,null,1,14,32046,[14,32046],1,1,0,0,-1,-1,1,1,0,0,1,1]}],"children":[],"data":["pHelix1",0,1,0,0]},{"id":32560,"path":"Assets\/Scenes\/Assets\/Prefabs\/howitzer.fbx","assetBundleId":-1,"components":[{"type":7,"id":33284,"data":[0,0,0,1,1,1,0,0,0,1]},{"type":11,"id":34400,"data":[12,34870]},{"type":13,"id":31682,"data":[null,null,1,14,32046,[14,32046],1,1,0,0,-1,-1,1,1,0,0,1,1]}],"children":[],"data":["planarTrimmedSurface1",0,1,0,0]},{"id":32562,"path":"Assets\/Scenes\/Assets\/Prefabs\/howitzer.fbx","assetBundleId":-1,"components":[{"type":7,"id":33286,"data":[0,0,0,1,1,1,0,0,0,1]},{"type":11,"id":34454,"data":[12,34474]},{"type":13,"id":32108,"data":[null,null,1,14,32046,[14,32046],1,1,0,0,-1,-1,1,1,0,0,1,1]}],"children":[],"data":["polySurface20",0,1,0,0]},{"id":32564,"path":"Assets\/Scenes\/Assets\/Prefabs\/howitzer.fbx","assetBundleId":-1,"components":[{"type":7,"id":33288,"data":[0,0,0,1,1,1,0,0,0,1]},{"type":11,"id":34112,"data":[12,34592]},{"type":13,"id":31952,"data":[null,null,1,14,31700,[14,31700],1,1,0,0,-1,-1,1,1,0,0,1,1]}],"children":[],"data":["polySurface21",0,1,0,0]},{"id":33866,"path":"Assets\/Scenes\/Assets\/Prefabs\/howitzer.fbx","assetBundleId":-1,"components":[{"type":7,"id":33290,"data":[0,0,0,1,1,1,0,0,0,1]},{"type":11,"id":34294,"data":[12,34936]},{"type":13,"id":31640,"data":[null,null,1,14,31624,[14,31624],1,1,0,0,-1,-1,1,1,0,0,1,1]}],"children":[],"data":["polySurface22",0,1,0,0]},{"id":32546,"path":"Assets\/Scenes\/Assets\/Prefabs\/howitzer.fbx","assetBundleId":-1,"components":[{"type":7,"id":33292,"data":[0,0,0,1,1,1,0,0,0,1]},{"type":11,"id":34296,"data":[12,34702]},{"type":13,"id":31948,"data":[null,null,1,14,34472,[14,34472],1,1,0,0,-1,-1,1,1,0,0,1,1]}],"children":[],"data":["polySurface55",0,1,0,0]},{"id":32544,"path":"Assets\/Scenes\/Assets\/Prefabs\/howitzer.fbx","assetBundleId":-1,"components":[{"type":7,"id":33294,"data":[0,0,0,1,1,1,0,0,0,1]},{"type":11,"id":34156,"data":[12,35010]},{"type":13,"id":31840,"data":[null,null,1,14,34472,[14,34472],1,1,0,0,-1,-1,1,1,0,0,1,1]}],"children":[],"data":["polySurface56",0,1,0,0]},{"id":32542,"path":"Assets\/Scenes\/Assets\/Prefabs\/howitzer.fbx","assetBundleId":-1,"components":[{"type":7,"id":33296,"data":[0,0,0,1,1,1,0,0,0,1]},{"type":11,"id":34306,"data":[12,34660]},{"type":13,"id":31822,"data":[null,null,1,14,34472,[14,34472],1,1,0,0,-1,-1,1,1,0,0,1,1]}],"children":[],"data":["polySurface57",0,1,0,0]},{"id":32540,"path":"Assets\/Scenes\/Assets\/Prefabs\/howitzer.fbx","assetBundleId":-1,"components":[{"type":7,"id":33298,"data":[0,0,0,1,1,1,0,0,0,1]},{"type":11,"id":34414,"data":[12,34866]},{"type":13,"id":32102,"data":[null,null,1,14,34472,[14,34472],1,1,0,0,-1,-1,1,1,0,0,1,1]}],"children":[],"data":["polySurface58",0,1,0,0]},{"id":32538,"path":"Assets\/Scenes\/Assets\/Prefabs\/howitzer.fbx","assetBundleId":-1,"components":[{"type":7,"id":33300,"data":[0,0,0,1,1,1,0,0,0,1]},{"type":11,"id":34442,"data":[12,34496]},{"type":13,"id":31896,"data":[null,null,1,14,34472,[14,34472],1,1,0,0,-1,-1,1,1,0,0,1,1]}],"children":[],"data":["polySurface59",0,1,0,0]},{"id":32536,"path":"Assets\/Scenes\/Assets\/Prefabs\/howitzer.fbx","assetBundleId":-1,"components":[{"type":7,"id":33302,"data":[0,0,0,1,1,1,0,0,0,1]},{"type":11,"id":34166,"data":[12,34484]},{"type":13,"id":31912,"data":[null,null,1,14,34472,[14,34472],1,1,0,0,-1,-1,1,1,0,0,1,1]}],"children":[],"data":["polySurface60",0,1,0,0]},{"id":32534,"path":"Assets\/Scenes\/Assets\/Prefabs\/howitzer.fbx","assetBundleId":-1,"components":[{"type":7,"id":33304,"data":[0,0,0,1,1,1,0,0,0,1]},{"type":11,"id":34370,"data":[12,34822]},{"type":13,"id":31768,"data":[null,null,1,14,34472,[14,34472],1,1,0,0,-1,-1,1,1,0,0,1,1]}],"children":[],"data":["polySurface61",0,1,0,0]},{"id":32532,"path":"Assets\/Scenes\/Assets\/Prefabs\/howitzer.fbx","assetBundleId":-1,"components":[{"type":7,"id":33306,"data":[0,0,0,1,1,1,0,0,0,1]},{"type":11,"id":33924,"data":[12,34536]},{"type":13,"id":31866,"data":[null,null,1,14,34472,[14,34472],1,1,0,0,-1,-1,1,1,0,0,1,1]}],"children":[],"data":["polySurface62",0,1,0,0]},{"id":32530,"path":"Assets\/Scenes\/Assets\/Prefabs\/howitzer.fbx","assetBundleId":-1,"components":[{"type":7,"id":33308,"data":[0,0,0,1,1,1,0,0,0,1]},{"type":11,"id":33998,"data":[12,34846]},{"type":13,"id":31724,"data":[null,null,1,14,31624,[14,31624],1,1,0,0,-1,-1,1,1,0,0,1,1]}],"children":[],"data":["polySurface63",0,1,0,0]},{"id":32528,"path":"Assets\/Scenes\/Assets\/Prefabs\/howitzer.fbx","assetBundleId":-1,"components":[{"type":7,"id":33310,"data":[0,0,0,1,1,1,0,0,0,1]},{"type":11,"id":34078,"data":[12,34674]},{"type":13,"id":32010,"data":[null,null,1,14,31624,[14,31624],1,1,0,0,-1,-1,1,1,0,0,1,1]}],"children":[],"data":["polySurface64",0,1,0,0]},{"id":32526,"path":"Assets\/Scenes\/Assets\/Prefabs\/howitzer.fbx","assetBundleId":-1,"components":[{"type":7,"id":33312,"data":[0,0,0,1,1,1,0,0,0,1]},{"type":11,"id":33940,"data":[12,34488]},{"type":13,"id":32028,"data":[null,null,1,14,34472,[14,34472],1,1,0,0,-1,-1,1,1,0,0,1,1]}],"children":[],"data":["polySurface65",0,1,0,0]},{"id":32524,"path":"Assets\/Scenes\/Assets\/Prefabs\/howitzer.fbx","assetBundleId":-1,"components":[{"type":7,"id":33314,"data":[0,0,0,1,1,1,0,0,0,1]},{"type":11,"id":34020,"data":[12,34548]},{"type":13,"id":31996,"data":[null,null,1,14,34472,[14,34472],1,1,0,0,-1,-1,1,1,0,0,1,1]}],"children":[],"data":["polySurface66",0,1,0,0]},{"id":32522,"path":"Assets\/Scenes\/Assets\/Prefabs\/howitzer.fbx","assetBundleId":-1,"components":[{"type":7,"id":33316,"data":[0,0,0,1,1,1,0,0,0,1]},{"type":11,"id":34068,"data":[12,34716]},{"type":13,"id":31704,"data":[null,null,1,14,34472,[14,34472],1,1,0,0,-1,-1,1,1,0,0,1,1]}],"children":[],"data":["polySurface67",0,1,0,0]},{"id":32520,"path":"Assets\/Scenes\/Assets\/Prefabs\/howitzer.fbx","assetBundleId":-1,"components":[{"type":7,"id":33318,"data":[0,0,0,1,1,1,0,0,0,1]},{"type":11,"id":33988,"data":[12,34580]},{"type":13,"id":32040,"data":[null,null,1,14,34472,[14,34472],1,1,0,0,-1,-1,1,1,0,0,1,1]}],"children":[],"data":["polySurface68",0,1,0,0]},{"id":32518,"path":"Assets\/Scenes\/Assets\/Prefabs\/howitzer.fbx","assetBundleId":-1,"components":[{"type":7,"id":33320,"data":[0,0,0,1,1,1,0,0,0,1]},{"type":11,"id":34194,"data":[12,34792]},{"type":13,"id":31848,"data":[null,null,1,14,34472,[14,34472],1,1,0,0,-1,-1,1,1,0,0,1,1]}],"children":[],"data":["polySurface69",0,1,0,0]},{"id":32516,"path":"Assets\/Scenes\/Assets\/Prefabs\/howitzer.fbx","assetBundleId":-1,"components":[{"type":7,"id":33322,"data":[0,0,0,1,1,1,0,0,0,1]},{"type":11,"id":34104,"data":[12,34586]},{"type":13,"id":31646,"data":[null,null,1,14,34472,[14,34472],1,1,0,0,-1,-1,1,1,0,0,1,1]}],"children":[],"data":["polySurface70",0,1,0,0]},{"id":32514,"path":"Assets\/Scenes\/Assets\/Prefabs\/howitzer.fbx","assetBundleId":-1,"components":[{"type":7,"id":33324,"data":[0,0,0,1,1,1,0,0,0,1]},{"type":11,"id":34024,"data":[12,34882]},{"type":13,"id":31830,"data":[null,null,1,14,34472,[14,34472],1,1,0,0,-1,-1,1,1,0,0,1,1]}],"children":[],"data":["polySurface71",0,1,0,0]},{"id":32512,"path":"Assets\/Scenes\/Assets\/Prefabs\/howitzer.fbx","assetBundleId":-1,"components":[{"type":7,"id":33326,"data":[0,0,0,1,1,1,0,0,0,1]},{"type":11,"id":34066,"data":[12,34720]},{"type":13,"id":31734,"data":[null,null,1,14,34472,[14,34472],1,1,0,0,-1,-1,1,1,0,0,1,1]}],"children":[],"data":["polySurface72",0,1,0,0]},{"id":32510,"path":"Assets\/Scenes\/Assets\/Prefabs\/howitzer.fbx","assetBundleId":-1,"components":[{"type":7,"id":33328,"data":[0,0,0,1,1,1,0,0,0,1]},{"type":11,"id":34406,"data":[12,34698]},{"type":13,"id":31998,"data":[null,null,1,14,34472,[14,34472],1,1,0,0,-1,-1,1,1,0,0,1,1]}],"children":[],"data":["polySurface73",0,1,0,0]},{"id":32508,"path":"Assets\/Scenes\/Assets\/Prefabs\/howitzer.fbx","assetBundleId":-1,"components":[{"type":7,"id":33330,"data":[0,0,0,1,1,1,0,0,0,1]},{"type":11,"id":34034,"data":[12,35028]},{"type":13,"id":31740,"data":[null,null,1,14,34472,[14,34472],1,1,0,0,-1,-1,1,1,0,0,1,1]}],"children":[],"data":["polySurface74",0,1,0,0]},{"id":32506,"path":"Assets\/Scenes\/Assets\/Prefabs\/howitzer.fbx","assetBundleId":-1,"components":[{"type":7,"id":33332,"data":[0,0,0,1,1,1,0,0,0,1]},{"type":11,"id":33970,"data":[12,34568]},{"type":13,"id":31904,"data":[null,null,1,14,34472,[14,34472],1,1,0,0,-1,-1,1,1,0,0,1,1]}],"children":[],"data":["polySurface75",0,1,0,0]},{"id":32504,"path":"Assets\/Scenes\/Assets\/Prefabs\/howitzer.fbx","assetBundleId":-1,"components":[{"type":7,"id":33334,"data":[0,0,0,1,1,1,0,0,0,1]},{"type":11,"id":34216,"data":[12,34714]},{"type":13,"id":31656,"data":[null,null,1,14,34472,[14,34472],1,1,0,0,-1,-1,1,1,0,0,1,1]}],"children":[],"data":["polySurface76",0,1,0,0]},{"id":32502,"path":"Assets\/Scenes\/Assets\/Prefabs\/howitzer.fbx","assetBundleId":-1,"components":[{"type":7,"id":33336,"data":[0,0,0,1,1,1,0,0,0,1]},{"type":11,"id":33960,"data":[12,35006]},{"type":13,"id":32176,"data":[null,null,1,14,34472,[14,34472],1,1,0,0,-1,-1,1,1,0,0,1,1]}],"children":[],"data":["polySurface77",0,1,0,0]},{"id":32500,"path":"Assets\/Scenes\/Assets\/Prefabs\/howitzer.fbx","assetBundleId":-1,"components":[{"type":7,"id":33338,"data":[0,0,0,1,1,1,0,0,0,1]},{"type":11,"id":34198,"data":[12,34560]},{"type":13,"id":32180,"data":[null,null,1,14,34472,[14,34472],1,1,0,0,-1,-1,1,1,0,0,1,1]}],"children":[],"data":["polySurface78",0,1,0,0]},{"id":32498,"path":"Assets\/Scenes\/Assets\/Prefabs\/howitzer.fbx","assetBundleId":-1,"components":[{"type":7,"id":33340,"data":[0,0,0,1,1,1,0,0,0,1]},{"type":11,"id":33962,"data":[12,34998]},{"type":13,"id":31648,"data":[null,null,1,14,34472,[14,34472],1,1,0,0,-1,-1,1,1,0,0,1,1]}],"children":[],"data":["polySurface79",0,1,0,0]},{"id":32496,"path":"Assets\/Scenes\/Assets\/Prefabs\/howitzer.fbx","assetBundleId":-1,"components":[{"type":7,"id":33342,"data":[0,0,0,1,1,1,0,0,0,1]},{"type":11,"id":34022,"data":[12,34926]},{"type":13,"id":32084,"data":[null,null,1,14,34472,[14,34472],1,1,0,0,-1,-1,1,1,0,0,1,1]}],"children":[],"data":["polySurface80",0,1,0,0]},{"id":32494,"path":"Assets\/Scenes\/Assets\/Prefabs\/howitzer.fbx","assetBundleId":-1,"components":[{"type":7,"id":33344,"data":[0,0,0,1,1,1,0,0,0,1]},{"type":11,"id":34424,"data":[12,34736]},{"type":13,"id":31812,"data":[null,null,1,14,34472,[14,34472],1,1,0,0,-1,-1,1,1,0,0,1,1]}],"children":[],"data":["polySurface81",0,1,0,0]},{"id":32492,"path":"Assets\/Scenes\/Assets\/Prefabs\/howitzer.fbx","assetBundleId":-1,"components":[{"type":7,"id":33346,"data":[0,0,0,1,1,1,0,0,0,1]},{"type":11,"id":34376,"data":[12,34776]},{"type":13,"id":31762,"data":[null,null,1,14,34472,[14,34472],1,1,0,0,-1,-1,1,1,0,0,1,1]}],"children":[],"data":["polySurface82",0,1,0,0]},{"id":32490,"path":"Assets\/Scenes\/Assets\/Prefabs\/howitzer.fbx","assetBundleId":-1,"components":[{"type":7,"id":33348,"data":[0,0,0,1,1,1,0,0,0,1]},{"type":11,"id":33994,"data":[12,34848]},{"type":13,"id":31806,"data":[null,null,1,14,34472,[14,34472],1,1,0,0,-1,-1,1,1,0,0,1,1]}],"children":[],"data":["polySurface83",0,1,0,0]},{"id":32488,"path":"Assets\/Scenes\/Assets\/Prefabs\/howitzer.fbx","assetBundleId":-1,"components":[{"type":7,"id":33350,"data":[0,0,0,1,1,1,0,0,0,1]},{"type":11,"id":34440,"data":[12,34596]},{"type":13,"id":31732,"data":[null,null,1,14,34472,[14,34472],1,1,0,0,-1,-1,1,1,0,0,1,1]}],"children":[],"data":["polySurface84",0,1,0,0]},{"id":32486,"path":"Assets\/Scenes\/Assets\/Prefabs\/howitzer.fbx","assetBundleId":-1,"components":[{"type":7,"id":33352,"data":[0,0,0,1,1,1,0,0,0,1]},{"type":11,"id":34092,"data":[12,34988]},{"type":13,"id":32074,"data":[null,null,1,14,34472,[14,34472],1,1,0,0,-1,-1,1,1,0,0,1,1]}],"children":[],"data":["polySurface85",0,1,0,0]},{"id":32484,"path":"Assets\/Scenes\/Assets\/Prefabs\/howitzer.fbx","assetBundleId":-1,"components":[{"type":7,"id":33354,"data":[0,0,0,1,1,1,0,0,0,1]},{"type":11,"id":34196,"data":[12,34922]},{"type":13,"id":32164,"data":[null,null,1,14,34472,[14,34472],1,1,0,0,-1,-1,1,1,0,0,1,1]}],"children":[],"data":["polySurface86",0,1,0,0]},{"id":32482,"path":"Assets\/Scenes\/Assets\/Prefabs\/howitzer.fbx","assetBundleId":-1,"components":[{"type":7,"id":33356,"data":[0,0,0,1,1,1,0,0,0,1]},{"type":11,"id":34132,"data":[12,34738]},{"type":13,"id":31694,"data":[null,null,1,14,34472,[14,34472],1,1,0,0,-1,-1,1,1,0,0,1,1]}],"children":[],"data":["polySurface87",0,1,0,0]},{"id":32480,"path":"Assets\/Scenes\/Assets\/Prefabs\/howitzer.fbx","assetBundleId":-1,"components":[{"type":7,"id":33358,"data":[0,0,0,1,1,1,0,0,0,1]},{"type":11,"id":34426,"data":[12,34676]},{"type":13,"id":31744,"data":[null,null,1,14,34472,[14,34472],1,1,0,0,-1,-1,1,1,0,0,1,1]}],"children":[],"data":["polySurface88",0,1,0,0]},{"id":32478,"path":"Assets\/Scenes\/Assets\/Prefabs\/howitzer.fbx","assetBundleId":-1,"components":[{"type":7,"id":33360,"data":[0,0,0,1,1,1,0,0,0,1]},{"type":11,"id":34246,"data":[12,34706]},{"type":13,"id":31926,"data":[null,null,1,14,34472,[14,34472],1,1,0,0,-1,-1,1,1,0,0,1,1]}],"children":[],"data":["polySurface89",0,1,0,0]},{"id":32476,"path":"Assets\/Scenes\/Assets\/Prefabs\/howitzer.fbx","assetBundleId":-1,"components":[{"type":7,"id":33362,"data":[0,0,0,1,1,1,0,0,0,1]},{"type":11,"id":34326,"data":[12,34964]},{"type":13,"id":31916,"data":[null,null,1,14,34472,[14,34472],1,1,0,0,-1,-1,1,1,0,0,1,1]}],"children":[],"data":["polySurface90",0,1,0,0]},{"id":32474,"path":"Assets\/Scenes\/Assets\/Prefabs\/howitzer.fbx","assetBundleId":-1,"components":[{"type":7,"id":33364,"data":[0,0,0,1,1,1,0,0,0,1]},{"type":11,"id":33974,"data":[12,34692]},{"type":13,"id":31876,"data":[null,null,1,14,34472,[14,34472],1,1,0,0,-1,-1,1,1,0,0,1,1]}],"children":[],"data":["polySurface91",0,1,0,0]},{"id":32472,"path":"Assets\/Scenes\/Assets\/Prefabs\/howitzer.fbx","assetBundleId":-1,"components":[{"type":7,"id":33366,"data":[0,0,0,1,1,1,0,0,0,1]},{"type":11,"id":34322,"data":[12,34632]},{"type":13,"id":32134,"data":[null,null,1,14,34472,[14,34472],1,1,0,0,-1,-1,1,1,0,0,1,1]}],"children":[],"data":["polySurface92",0,1,0,0]},{"id":32470,"path":"Assets\/Scenes\/Assets\/Prefabs\/howitzer.fbx","assetBundleId":-1,"components":[{"type":7,"id":33368,"data":[0,0,0,1,1,1,0,0,0,1]},{"type":11,"id":34060,"data":[12,34780]},{"type":13,"id":31796,"data":[null,null,1,14,34472,[14,34472],1,1,0,0,-1,-1,1,1,0,0,1,1]}],"children":[],"data":["polySurface93",0,1,0,0]},{"id":32468,"path":"Assets\/Scenes\/Assets\/Prefabs\/howitzer.fbx","assetBundleId":-1,"components":[{"type":7,"id":33370,"data":[0,0,0,1,1,1,0,0,0,1]},{"type":11,"id":34320,"data":[12,34900]},{"type":13,"id":31792,"data":[null,null,1,14,34472,[14,34472],1,1,0,0,-1,-1,1,1,0,0,1,1]}],"children":[],"data":["polySurface94",0,1,0,0]},{"id":32466,"path":"Assets\/Scenes\/Assets\/Prefabs\/howitzer.fbx","assetBundleId":-1,"components":[{"type":7,"id":33372,"data":[0,0,0,1,1,1,0,0,0,1]},{"type":11,"id":34118,"data":[12,34942]},{"type":13,"id":31932,"data":[null,null,1,14,34472,[14,34472],1,1,0,0,-1,-1,1,1,0,0,1,1]}],"children":[],"data":["polySurface95",0,1,0,0]},{"id":32464,"path":"Assets\/Scenes\/Assets\/Prefabs\/howitzer.fbx","assetBundleId":-1,"components":[{"type":7,"id":33374,"data":[0,0,0,1,1,1,0,0,0,1]},{"type":11,"id":34316,"data":[12,34682]},{"type":13,"id":31960,"data":[null,null,1,14,34472,[14,34472],1,1,0,0,-1,-1,1,1,0,0,1,1]}],"children":[],"data":["polySurface96",0,1,0,0]},{"id":32462,"path":"Assets\/Scenes\/Assets\/Prefabs\/howitzer.fbx","assetBundleId":-1,"components":[{"type":7,"id":33376,"data":[0,0,0,1,1,1,0,0,0,1]},{"type":11,"id":34190,"data":[12,34808]},{"type":13,"id":32038,"data":[null,null,1,14,34472,[14,34472],1,1,0,0,-1,-1,1,1,0,0,1,1]}],"children":[],"data":["polySurface105",0,1,0,0]},{"id":32460,"path":"Assets\/Scenes\/Assets\/Prefabs\/howitzer.fbx","assetBundleId":-1,"components":[{"type":7,"id":33378,"data":[0,0,0,1,1,1,0,0,0,1]},{"type":11,"id":34064,"data":[12,34990]},{"type":13,"id":31686,"data":[null,null,1,14,34472,[14,34472],1,1,0,0,-1,-1,1,1,0,0,1,1]}],"children":[],"data":["polySurface106",0,1,0,0]},{"id":32458,"path":"Assets\/Scenes\/Assets\/Prefabs\/howitzer.fbx","assetBundleId":-1,"components":[{"type":7,"id":33380,"data":[0,0,0,1,1,1,0,0,0,1]},{"type":11,"id":34144,"data":[12,34790]},{"type":13,"id":31730,"data":[null,null,1,14,34472,[14,34472],1,1,0,0,-1,-1,1,1,0,0,1,1]}],"children":[],"data":["polySurface107",0,1,0,0]},{"id":32456,"path":"Assets\/Scenes\/Assets\/Prefabs\/howitzer.fbx","assetBundleId":-1,"components":[{"type":7,"id":33382,"data":[0,0,0,1,1,1,0,0,0,1]},{"type":11,"id":34030,"data":[12,34984]},{"type":13,"id":31870,"data":[null,null,1,14,34472,[14,34472],1,1,0,0,-1,-1,1,1,0,0,1,1]}],"children":[],"data":["polySurface108",0,1,0,0]},{"id":32454,"path":"Assets\/Scenes\/Assets\/Prefabs\/howitzer.fbx","assetBundleId":-1,"components":[{"type":7,"id":33384,"data":[0,0,0,1,1,1,0,0,0,1]},{"type":11,"id":34120,"data":[12,34718]},{"type":13,"id":31816,"data":[null,null,1,14,34472,[14,34472],1,1,0,0,-1,-1,1,1,0,0,1,1]}],"children":[],"data":["polySurface109",0,1,0,0]},{"id":32452,"path":"Assets\/Scenes\/Assets\/Prefabs\/howitzer.fbx","assetBundleId":-1,"components":[{"type":7,"id":33386,"data":[0,0,0,1,1,1,0,0,0,1]},{"type":11,"id":34254,"data":[12,34982]},{"type":13,"id":32036,"data":[null,null,1,14,34472,[14,34472],1,1,0,0,-1,-1,1,1,0,0,1,1]}],"children":[],"data":["polySurface110",0,1,0,0]},{"id":32450,"path":"Assets\/Scenes\/Assets\/Prefabs\/howitzer.fbx","assetBundleId":-1,"components":[{"type":7,"id":33388,"data":[0,0,0,1,1,1,0,0,0,1]},{"type":11,"id":34372,"data":[12,34802]},{"type":13,"id":31800,"data":[null,null,1,14,34472,[14,34472],1,1,0,0,-1,-1,1,1,0,0,1,1]}],"children":[],"data":["polySurface111",0,1,0,0]},{"id":32448,"path":"Assets\/Scenes\/Assets\/Prefabs\/howitzer.fbx","assetBundleId":-1,"components":[{"type":7,"id":33390,"data":[0,0,0,1,1,1,0,0,0,1]},{"type":11,"id":33944,"data":[12,34834]},{"type":13,"id":31836,"data":[null,null,1,14,34472,[14,34472],1,1,0,0,-1,-1,1,1,0,0,1,1]}],"children":[],"data":["polySurface112",0,1,0,0]},{"id":32446,"path":"Assets\/Scenes\/Assets\/Prefabs\/howitzer.fbx","assetBundleId":-1,"components":[{"type":7,"id":33392,"data":[0,0,0,1,1,1,0,0,0,1]},{"type":11,"id":34344,"data":[12,34532]},{"type":13,"id":31760,"data":[null,null,1,14,34472,[14,34472],1,1,0,0,-1,-1,1,1,0,0,1,1]}],"children":[],"data":["polySurface113",0,1,0,0]},{"id":32444,"path":"Assets\/Scenes\/Assets\/Prefabs\/howitzer.fbx","assetBundleId":-1,"components":[{"type":7,"id":33394,"data":[0,0,0,1,1,1,0,0,0,1]},{"type":11,"id":33982,"data":[12,34970]},{"type":13,"id":31654,"data":[null,null,1,14,34472,[14,34472],1,1,0,0,-1,-1,1,1,0,0,1,1]}],"children":[],"data":["polySurface114",0,1,0,0]},{"id":32442,"path":"Assets\/Scenes\/Assets\/Prefabs\/howitzer.fbx","assetBundleId":-1,"components":[{"type":7,"id":33396,"data":[0,0,0,1,1,1,0,0,0,1]},{"type":11,"id":34052,"data":[12,35014]},{"type":13,"id":32004,"data":[null,null,1,14,34472,[14,34472],1,1,0,0,-1,-1,1,1,0,0,1,1]}],"children":[],"data":["polySurface115",0,1,0,0]},{"id":32440,"path":"Assets\/Scenes\/Assets\/Prefabs\/howitzer.fbx","assetBundleId":-1,"components":[{"type":7,"id":33398,"data":[0,0,0,1,1,1,0,0,0,1]},{"type":11,"id":34004,"data":[12,34604]},{"type":13,"id":31864,"data":[null,null,1,14,34472,[14,34472],1,1,0,0,-1,-1,1,1,0,0,1,1]}],"children":[],"data":["polySurface116",0,1,0,0]},{"id":32438,"path":"Assets\/Scenes\/Assets\/Prefabs\/howitzer.fbx","assetBundleId":-1,"components":[{"type":7,"id":33400,"data":[0,0,0,1,1,1,0,0,0,1]},{"type":11,"id":34170,"data":[12,34572]},{"type":13,"id":31986,"data":[null,null,1,14,34472,[14,34472],1,1,0,0,-1,-1,1,1,0,0,1,1]}],"children":[],"data":["polySurface117",0,1,0,0]},{"id":32436,"path":"Assets\/Scenes\/Assets\/Prefabs\/howitzer.fbx","assetBundleId":-1,"components":[{"type":7,"id":33402,"data":[0,0,0,1,1,1,0,0,0,1]},{"type":11,"id":34090,"data":[12,34920]},{"type":13,"id":31684,"data":[null,null,1,14,34472,[14,34472],1,1,0,0,-1,-1,1,1,0,0,1,1]}],"children":[],"data":["polySurface118",0,1,0,0]},{"id":32434,"path":"Assets\/Scenes\/Assets\/Prefabs\/howitzer.fbx","assetBundleId":-1,"components":[{"type":7,"id":33404,"data":[0,0,0,1,1,1,0,0,0,1]},{"type":11,"id":34332,"data":[12,34712]},{"type":13,"id":32160,"data":[null,null,1,14,34472,[14,34472],1,1,0,0,-1,-1,1,1,0,0,1,1]}],"children":[],"data":["polySurface119",0,1,0,0]},{"id":32432,"path":"Assets\/Scenes\/Assets\/Prefabs\/howitzer.fbx","assetBundleId":-1,"components":[{"type":7,"id":33406,"data":[0,0,0,1,1,1,0,0,0,1]},{"type":11,"id":34148,"data":[12,34898]},{"type":13,"id":31924,"data":[null,null,1,14,34472,[14,34472],1,1,0,0,-1,-1,1,1,0,0,1,1]}],"children":[],"data":["polySurface120",0,1,0,0]},{"id":32430,"path":"Assets\/Scenes\/Assets\/Prefabs\/howitzer.fbx","assetBundleId":-1,"components":[{"type":7,"id":33408,"data":[0,0,0,1,1,1,0,0,0,1]},{"type":11,"id":34242,"data":[12,34840]},{"type":13,"id":32078,"data":[null,null,1,14,34472,[14,34472],1,1,0,0,-1,-1,1,1,0,0,1,1]}],"children":[],"data":["polySurface121",0,1,0,0]},{"id":32428,"path":"Assets\/Scenes\/Assets\/Prefabs\/howitzer.fbx","assetBundleId":-1,"components":[{"type":7,"id":33410,"data":[0,0,0,1,1,1,0,0,0,1]},{"type":11,"id":33984,"data":[12,34878]},{"type":13,"id":32012,"data":[null,null,1,14,34472,[14,34472],1,1,0,0,-1,-1,1,1,0,0,1,1]}],"children":[],"data":["polySurface122",0,1,0,0]},{"id":32426,"path":"Assets\/Scenes\/Assets\/Prefabs\/howitzer.fbx","assetBundleId":-1,"components":[{"type":7,"id":33412,"data":[0,0,0,1,1,1,0,0,0,1]},{"type":11,"id":33956,"data":[12,34646]},{"type":13,"id":31708,"data":[null,null,1,14,34472,[14,34472],1,1,0,0,-1,-1,1,1,0,0,1,1]}],"children":[],"data":["polySurface123",0,1,0,0]},{"id":32424,"path":"Assets\/Scenes\/Assets\/Prefabs\/howitzer.fbx","assetBundleId":-1,"components":[{"type":7,"id":33414,"data":[0,0,0,1,1,1,0,0,0,1]},{"type":11,"id":34252,"data":[12,34902]},{"type":13,"id":32182,"data":[null,null,1,14,34472,[14,34472],1,1,0,0,-1,-1,1,1,0,0,1,1]}],"children":[],"data":["polySurface124",0,1,0,0]},{"id":32422,"path":"Assets\/Scenes\/Assets\/Prefabs\/howitzer.fbx","assetBundleId":-1,"components":[{"type":7,"id":33416,"data":[0,0,0,1,1,1,0,0,0,1]},{"type":11,"id":33910,"data":[12,34550]},{"type":13,"id":31628,"data":[null,null,1,14,34472,[14,34472],1,1,0,0,-1,-1,1,1,0,0,1,1]}],"children":[],"data":["polySurface125",0,1,0,0]},{"id":32420,"path":"Assets\/Scenes\/Assets\/Prefabs\/howitzer.fbx","assetBundleId":-1,"components":[{"type":7,"id":33418,"data":[0,0,0,1,1,1,0,0,0,1]},{"type":11,"id":34142,"data":[12,34818]},{"type":13,"id":31678,"data":[null,null,1,14,34472,[14,34472],1,1,0,0,-1,-1,1,1,0,0,1,1]}],"children":[],"data":["polySurface126",0,1,0,0]},{"id":32418,"path":"Assets\/Scenes\/Assets\/Prefabs\/howitzer.fbx","assetBundleId":-1,"components":[{"type":7,"id":33420,"data":[0,0,0,1,1,1,0,0,0,1]},{"type":11,"id":34040,"data":[12,34842]},{"type":13,"id":31688,"data":[null,null,1,14,34472,[14,34472],1,1,0,0,-1,-1,1,1,0,0,1,1]}],"children":[],"data":["polySurface127",0,1,0,0]},{"id":32416,"path":"Assets\/Scenes\/Assets\/Prefabs\/howitzer.fbx","assetBundleId":-1,"components":[{"type":7,"id":33422,"data":[0,0,0,1,1,1,0,0,0,1]},{"type":11,"id":34284,"data":[12,34908]},{"type":13,"id":31630,"data":[null,null,1,14,34472,[14,34472],1,1,0,0,-1,-1,1,1,0,0,1,1]}],"children":[],"data":["polySurface137",0,1,0,0]},{"id":32414,"path":"Assets\/Scenes\/Assets\/Prefabs\/howitzer.fbx","assetBundleId":-1,"components":[{"type":7,"id":33424,"data":[0,0,0,1,1,1,0,0,0,1]},{"type":11,"id":34330,"data":[12,34742]},{"type":13,"id":31638,"data":[null,null,1,14,34472,[14,34472],1,1,0,0,-1,-1,1,1,0,0,1,1]}],"children":[],"data":["polySurface138",0,1,0,0]},{"id":32412,"path":"Assets\/Scenes\/Assets\/Prefabs\/howitzer.fbx","assetBundleId":-1,"components":[{"type":7,"id":33426,"data":[0,0,0,1,1,1,0,0,0,1]},{"type":11,"id":34160,"data":[12,34594]},{"type":13,"id":31810,"data":[null,null,1,14,34472,[14,34472],1,1,0,0,-1,-1,1,1,0,0,1,1]}],"children":[],"data":["polySurface139",0,1,0,0]},{"id":32410,"path":"Assets\/Scenes\/Assets\/Prefabs\/howitzer.fbx","assetBundleId":-1,"components":[{"type":7,"id":33428,"data":[0,0,0,1,1,1,0,0,0,1]},{"type":11,"id":33980,"data":[12,34578]},{"type":13,"id":31936,"data":[null,null,1,14,34472,[14,34472],1,1,0,0,-1,-1,1,1,0,0,1,1]}],"children":[],"data":["polySurface140",0,1,0,0]},{"id":32408,"path":"Assets\/Scenes\/Assets\/Prefabs\/howitzer.fbx","assetBundleId":-1,"components":[{"type":7,"id":33430,"data":[0,0,0,1,1,1,0,0,0,1]},{"type":11,"id":33908,"data":[12,34996]},{"type":13,"id":31764,"data":[null,null,1,14,34472,[14,34472],1,1,0,0,-1,-1,1,1,0,0,1,1]}],"children":[],"data":["polySurface141",0,1,0,0]},{"id":32406,"path":"Assets\/Scenes\/Assets\/Prefabs\/howitzer.fbx","assetBundleId":-1,"components":[{"type":7,"id":33432,"data":[0,0,0,1,1,1,0,0,0,1]},{"type":11,"id":34420,"data":[12,34510]},{"type":13,"id":32152,"data":[null,null,1,14,34472,[14,34472],1,1,0,0,-1,-1,1,1,0,0,1,1]}],"children":[],"data":["polySurface147",0,1,0,0]},{"id":32404,"path":"Assets\/Scenes\/Assets\/Prefabs\/howitzer.fbx","assetBundleId":-1,"components":[{"type":7,"id":33434,"data":[0,0,0,1,1,1,0,0,0,1]},{"type":11,"id":34452,"data":[12,34948]},{"type":13,"id":31962,"data":[null,null,1,14,34472,[14,34472],1,1,0,0,-1,-1,1,1,0,0,1,1]}],"children":[],"data":["polySurface148",0,1,0,0]},{"id":32402,"path":"Assets\/Scenes\/Assets\/Prefabs\/howitzer.fbx","assetBundleId":-1,"components":[{"type":7,"id":33436,"data":[0,0,0,1,1,1,0,0,0,1]},{"type":11,"id":34288,"data":[12,34658]},{"type":13,"id":31922,"data":[null,null,1,14,34472,[14,34472],1,1,0,0,-1,-1,1,1,0,0,1,1]}],"children":[],"data":["polySurface149",0,1,0,0]},{"id":32400,"path":"Assets\/Scenes\/Assets\/Prefabs\/howitzer.fbx","assetBundleId":-1,"components":[{"type":7,"id":33438,"data":[0,0,0,1,1,1,0,0,0,1]},{"type":11,"id":34036,"data":[12,35022]},{"type":13,"id":32112,"data":[null,null,1,14,34472,[14,34472],1,1,0,0,-1,-1,1,1,0,0,1,1]}],"children":[],"data":["polySurface150",0,1,0,0]},{"id":32398,"path":"Assets\/Scenes\/Assets\/Prefabs\/howitzer.fbx","assetBundleId":-1,"components":[{"type":7,"id":33440,"data":[0,0,0,1,1,1,0,0,0,1]},{"type":11,"id":34248,"data":[12,34476]},{"type":13,"id":32068,"data":[null,null,1,14,34472,[14,34472],1,1,0,0,-1,-1,1,1,0,0,1,1]}],"children":[],"data":["polySurface151",0,1,0,0]},{"id":32396,"path":"Assets\/Scenes\/Assets\/Prefabs\/howitzer.fbx","assetBundleId":-1,"components":[{"type":7,"id":33442,"data":[0,0,0,1,1,1,0,0,0,1]},{"type":11,"id":33986,"data":[12,34768]},{"type":13,"id":32086,"data":[null,null,1,14,34472,[14,34472],1,1,0,0,-1,-1,1,1,0,0,1,1]}],"children":[],"data":["polySurface161",0,1,0,0]},{"id":32394,"path":"Assets\/Scenes\/Assets\/Prefabs\/howitzer.fbx","assetBundleId":-1,"components":[{"type":7,"id":33444,"data":[0,0,0,1,1,1,0,0,0,1]},{"type":11,"id":33938,"data":[12,34518]},{"type":13,"id":31874,"data":[null,null,1,14,34472,[14,34472],1,1,0,0,-1,-1,1,1,0,0,1,1]}],"children":[],"data":["polySurface162",0,1,0,0]},{"id":32392,"path":"Assets\/Scenes\/Assets\/Prefabs\/howitzer.fbx","assetBundleId":-1,"components":[{"type":7,"id":33446,"data":[0,0,0,1,1,1,0,0,0,1]},{"type":11,"id":34082,"data":[12,34976]},{"type":13,"id":32146,"data":[null,null,1,14,34472,[14,34472],1,1,0,0,-1,-1,1,1,0,0,1,1]}],"children":[],"data":["polySurface163",0,1,0,0]},{"id":32390,"path":"Assets\/Scenes\/Assets\/Prefabs\/howitzer.fbx","assetBundleId":-1,"components":[{"type":7,"id":33448,"data":[0,0,0,1,1,1,0,0,0,1]},{"type":11,"id":34226,"data":[12,34618]},{"type":13,"id":31750,"data":[null,null,1,14,34472,[14,34472],1,1,0,0,-1,-1,1,1,0,0,1,1]}],"children":[],"data":["polySurface164",0,1,0,0]},{"id":32388,"path":"Assets\/Scenes\/Assets\/Prefabs\/howitzer.fbx","assetBundleId":-1,"components":[{"type":7,"id":33450,"data":[0,0,0,1,1,1,0,0,0,1]},{"type":11,"id":33930,"data":[12,34566]},{"type":13,"id":32094,"data":[null,null,1,14,34472,[14,34472],1,1,0,0,-1,-1,1,1,0,0,1,1]}],"children":[],"data":["polySurface165",0,1,0,0]},{"id":32386,"path":"Assets\/Scenes\/Assets\/Prefabs\/howitzer.fbx","assetBundleId":-1,"components":[{"type":7,"id":33452,"data":[0,0,0,1,1,1,0,0,0,1]},{"type":11,"id":34450,"data":[12,34638]},{"type":13,"id":32118,"data":[null,null,1,14,34472,[14,34472],1,1,0,0,-1,-1,1,1,0,0,1,1]}],"children":[],"data":["polySurface171",0,1,0,0]},{"id":32384,"path":"Assets\/Scenes\/Assets\/Prefabs\/howitzer.fbx","assetBundleId":-1,"components":[{"type":7,"id":33454,"data":[0,0,0,1,1,1,0,0,0,1]},{"type":11,"id":34150,"data":[12,34522]},{"type":13,"id":31690,"data":[null,null,1,14,34472,[14,34472],1,1,0,0,-1,-1,1,1,0,0,1,1]}],"children":[],"data":["polySurface172",0,1,0,0]},{"id":32382,"path":"Assets\/Scenes\/Assets\/Prefabs\/howitzer.fbx","assetBundleId":-1,"components":[{"type":7,"id":33456,"data":[0,0,0,1,1,1,0,0,0,1]},{"type":11,"id":34282,"data":[12,34914]},{"type":13,"id":31782,"data":[null,null,1,14,34472,[14,34472],1,1,0,0,-1,-1,1,1,0,0,1,1]}],"children":[],"data":["polySurface173",0,1,0,0]},{"id":32380,"path":"Assets\/Scenes\/Assets\/Prefabs\/howitzer.fbx","assetBundleId":-1,"components":[{"type":7,"id":33458,"data":[0,0,0,1,1,1,0,0,0,1]},{"type":11,"id":34436,"data":[12,34478]},{"type":13,"id":32156,"data":[null,null,1,14,34472,[14,34472],1,1,0,0,-1,-1,1,1,0,0,1,1]}],"children":[],"data":["polySurface174",0,1,0,0]},{"id":32378,"path":"Assets\/Scenes\/Assets\/Prefabs\/howitzer.fbx","assetBundleId":-1,"components":[{"type":7,"id":33460,"data":[0,0,0,1,1,1,0,0,0,1]},{"type":11,"id":34434,"data":[12,34876]},{"type":13,"id":31802,"data":[null,null,1,14,34472,[14,34472],1,1,0,0,-1,-1,1,1,0,0,1,1]}],"children":[],"data":["polySurface175",0,1,0,0]},{"id":32376,"path":"Assets\/Scenes\/Assets\/Prefabs\/howitzer.fbx","assetBundleId":-1,"components":[{"type":7,"id":33462,"data":[0,0,0,1,1,1,0,0,0,1]},{"type":11,"id":34128,"data":[12,34554]},{"type":13,"id":31774,"data":[null,null,1,14,34472,[14,34472],1,1,0,0,-1,-1,1,1,0,0,1,1]}],"children":[],"data":["polySurface179",0,1,0,0]},{"id":32374,"path":"Assets\/Scenes\/Assets\/Prefabs\/howitzer.fbx","assetBundleId":-1,"components":[{"type":7,"id":33464,"data":[0,0,0,1,1,1,0,0,0,1]},{"type":11,"id":33996,"data":[12,34796]},{"type":13,"id":32014,"data":[null,null,1,14,34472,[14,34472],1,1,0,0,-1,-1,1,1,0,0,1,1]}],"children":[],"data":["polySurface180",0,1,0,0]},{"id":32372,"path":"Assets\/Scenes\/Assets\/Prefabs\/howitzer.fbx","assetBundleId":-1,"components":[{"type":7,"id":33466,"data":[0,0,0,1,1,1,0,0,0,1]},{"type":11,"id":34390,"data":[12,34652]},{"type":13,"id":31950,"data":[null,null,1,14,34472,[14,34472],1,1,0,0,-1,-1,1,1,0,0,1,1]}],"children":[],"data":["polySurface181",0,1,0,0]},{"id":32370,"path":"Assets\/Scenes\/Assets\/Prefabs\/howitzer.fbx","assetBundleId":-1,"components":[{"type":7,"id":33468,"data":[0,0,0,1,1,1,0,0,0,1]},{"type":11,"id":34268,"data":[12,34588]},{"type":13,"id":31920,"data":[null,null,1,14,34472,[14,34472],1,1,0,0,-1,-1,1,1,0,0,1,1]}],"children":[],"data":["polySurface185",0,1,0,0]},{"id":32368,"path":"Assets\/Scenes\/Assets\/Prefabs\/howitzer.fbx","assetBundleId":-1,"components":[{"type":7,"id":33470,"data":[0,0,0,1,1,1,0,0,0,1]},{"type":11,"id":34054,"data":[12,34520]},{"type":13,"id":31804,"data":[null,null,1,14,34472,[14,34472],1,1,0,0,-1,-1,1,1,0,0,1,1]}],"children":[],"data":["polySurface186",0,1,0,0]},{"id":32366,"path":"Assets\/Scenes\/Assets\/Prefabs\/howitzer.fbx","assetBundleId":-1,"components":[{"type":7,"id":33472,"data":[0,0,0,1,1,1,0,0,0,1]},{"type":11,"id":34236,"data":[12,34958]},{"type":13,"id":31742,"data":[null,null,1,14,34472,[14,34472],1,1,0,0,-1,-1,1,1,0,0,1,1]}],"children":[],"data":["polySurface187",0,1,0,0]},{"id":32364,"path":"Assets\/Scenes\/Assets\/Prefabs\/howitzer.fbx","assetBundleId":-1,"components":[{"type":7,"id":33474,"data":[0,0,0,1,1,1,0,0,0,1]},{"type":11,"id":34312,"data":[12,34584]},{"type":13,"id":31660,"data":[null,null,1,14,34472,[14,34472],1,1,0,0,-1,-1,1,1,0,0,1,1]}],"children":[],"data":["polySurface191",0,1,0,0]},{"id":32362,"path":"Assets\/Scenes\/Assets\/Prefabs\/howitzer.fbx","assetBundleId":-1,"components":[{"type":7,"id":33476,"data":[0,0,0,1,1,1,0,0,0,1]},{"type":11,"id":34328,"data":[12,34644]},{"type":13,"id":31956,"data":[null,null,1,14,34472,[14,34472],1,1,0,0,-1,-1,1,1,0,0,1,1]}],"children":[],"data":["polySurface192",0,1,0,0]},{"id":32360,"path":"Assets\/Scenes\/Assets\/Prefabs\/howitzer.fbx","assetBundleId":-1,"components":[{"type":7,"id":33478,"data":[0,0,0,1,1,1,0,0,0,1]},{"type":11,"id":33920,"data":[12,34766]},{"type":13,"id":31626,"data":[null,null,1,14,34472,[14,34472],1,1,0,0,-1,-1,1,1,0,0,1,1]}],"children":[],"data":["polySurface193",0,1,0,0]},{"id":32358,"path":"Assets\/Scenes\/Assets\/Prefabs\/howitzer.fbx","assetBundleId":-1,"components":[{"type":7,"id":33480,"data":[0,0,0,1,1,1,0,0,0,1]},{"type":11,"id":34410,"data":[12,34470]},{"type":13,"id":32148,"data":[null,null,1,14,34472,[14,34472],1,1,0,0,-1,-1,1,1,0,0,1,1]}],"children":[],"data":["polySurface197",0,1,0,0]},{"id":32356,"path":"Assets\/Scenes\/Assets\/Prefabs\/howitzer.fbx","assetBundleId":-1,"components":[{"type":7,"id":33482,"data":[0,0,0,1,1,1,0,0,0,1]},{"type":11,"id":34146,"data":[12,34628]},{"type":13,"id":31854,"data":[null,null,1,14,34472,[14,34472],1,1,0,0,-1,-1,1,1,0,0,1,1]}],"children":[],"data":["polySurface198",0,1,0,0]},{"id":32354,"path":"Assets\/Scenes\/Assets\/Prefabs\/howitzer.fbx","assetBundleId":-1,"components":[{"type":7,"id":33484,"data":[0,0,0,1,1,1,0,0,0,1]},{"type":11,"id":33918,"data":[12,34672]},{"type":13,"id":31930,"data":[null,null,1,14,34472,[14,34472],1,1,0,0,-1,-1,1,1,0,0,1,1]}],"children":[],"data":["polySurface199",0,1,0,0]},{"id":32352,"path":"Assets\/Scenes\/Assets\/Prefabs\/howitzer.fbx","assetBundleId":-1,"components":[{"type":7,"id":33486,"data":[0,0,0,1,1,1,0,0,0,1]},{"type":11,"id":34094,"data":[12,34564]},{"type":13,"id":31862,"data":[null,null,1,14,34472,[14,34472],1,1,0,0,-1,-1,1,1,0,0,1,1]}],"children":[],"data":["polySurface200",0,1,0,0]},{"id":32350,"path":"Assets\/Scenes\/Assets\/Prefabs\/howitzer.fbx","assetBundleId":-1,"components":[{"type":7,"id":33488,"data":[0,0,0,1,1,1,0,0,0,1]},{"type":11,"id":34192,"data":[12,34616]},{"type":13,"id":31954,"data":[null,null,1,14,34472,[14,34472],1,1,0,0,-1,-1,1,1,0,0,1,1]}],"children":[],"data":["polySurface201",0,1,0,0]},{"id":32348,"path":"Assets\/Scenes\/Assets\/Prefabs\/howitzer.fbx","assetBundleId":-1,"components":[{"type":7,"id":33490,"data":[0,0,0,1,1,1,0,0,0,1]},{"type":11,"id":34182,"data":[12,34516]},{"type":13,"id":31824,"data":[null,null,1,14,34472,[14,34472],1,1,0,0,-1,-1,1,1,0,0,1,1]}],"children":[],"data":["polySurface202",0,1,0,0]},{"id":32346,"path":"Assets\/Scenes\/Assets\/Prefabs\/howitzer.fbx","assetBundleId":-1,"components":[{"type":7,"id":33492,"data":[0,0,0,1,1,1,0,0,0,1]},{"type":11,"id":34168,"data":[12,34868]},{"type":13,"id":31868,"data":[null,null,1,14,34472,[14,34472],1,1,0,0,-1,-1,1,1,0,0,1,1]}],"children":[],"data":["polySurface203",0,1,0,0]},{"id":32344,"path":"Assets\/Scenes\/Assets\/Prefabs\/howitzer.fbx","assetBundleId":-1,"components":[{"type":7,"id":33494,"data":[0,0,0,1,1,1,0,0,0,1]},{"type":11,"id":34280,"data":[12,34582]},{"type":13,"id":31890,"data":[null,null,1,14,34472,[14,34472],1,1,0,0,-1,-1,1,1,0,0,1,1]}],"children":[],"data":["polySurface204",0,1,0,0]},{"id":32342,"path":"Assets\/Scenes\/Assets\/Prefabs\/howitzer.fbx","assetBundleId":-1,"components":[{"type":7,"id":33496,"data":[0,0,0,1,1,1,0,0,0,1]},{"type":11,"id":34364,"data":[12,34570]},{"type":13,"id":32088,"data":[null,null,1,14,34472,[14,34472],1,1,0,0,-1,-1,1,1,0,0,1,1]}],"children":[],"data":["polySurface205",0,1,0,0]},{"id":32340,"path":"Assets\/Scenes\/Assets\/Prefabs\/howitzer.fbx","assetBundleId":-1,"components":[{"type":7,"id":33498,"data":[0,0,0,1,1,1,0,0,0,1]},{"type":11,"id":34158,"data":[12,34494]},{"type":13,"id":32092,"data":[null,null,1,14,34472,[14,34472],1,1,0,0,-1,-1,1,1,0,0,1,1]}],"children":[],"data":["polySurface206",0,1,0,0]},{"id":32338,"path":"Assets\/Scenes\/Assets\/Prefabs\/howitzer.fbx","assetBundleId":-1,"components":[{"type":7,"id":33500,"data":[0,0,0,1,1,1,0,0,0,1]},{"type":11,"id":34394,"data":[12,34916]},{"type":13,"id":32142,"data":[null,null,1,14,34472,[14,34472],1,1,0,0,-1,-1,1,1,0,0,1,1]}],"children":[],"data":["polySurface207",0,1,0,0]},{"id":32336,"path":"Assets\/Scenes\/Assets\/Prefabs\/howitzer.fbx","assetBundleId":-1,"components":[{"type":7,"id":33502,"data":[0,0,0,1,1,1,0,0,0,1]},{"type":11,"id":34028,"data":[12,34664]},{"type":13,"id":31670,"data":[null,null,1,14,34472,[14,34472],1,1,0,0,-1,-1,1,1,0,0,1,1]}],"children":[],"data":["polySurface208",0,1,0,0]},{"id":32334,"path":"Assets\/Scenes\/Assets\/Prefabs\/howitzer.fbx","assetBundleId":-1,"components":[{"type":7,"id":33504,"data":[0,0,0,1,1,1,0,0,0,1]},{"type":11,"id":34354,"data":[12,34500]},{"type":13,"id":32104,"data":[null,null,1,14,34472,[14,34472],1,1,0,0,-1,-1,1,1,0,0,1,1]}],"children":[],"data":["polySurface209",0,1,0,0]},{"id":32332,"path":"Assets\/Scenes\/Assets\/Prefabs\/howitzer.fbx","assetBundleId":-1,"components":[{"type":7,"id":33506,"data":[0,0,0,1,1,1,0,0,0,1]},{"type":11,"id":34136,"data":[12,34880]},{"type":13,"id":31828,"data":[null,null,1,14,34472,[14,34472],1,1,0,0,-1,-1,1,1,0,0,1,1]}],"children":[],"data":["polySurface210",0,1,0,0]},{"id":32330,"path":"Assets\/Scenes\/Assets\/Prefabs\/howitzer.fbx","assetBundleId":-1,"components":[{"type":7,"id":33508,"data":[0,0,0,1,1,1,0,0,0,1]},{"type":11,"id":34378,"data":[12,34950]},{"type":13,"id":31672,"data":[null,null,1,14,34472,[14,34472],1,1,0,0,-1,-1,1,1,0,0,1,1]}],"children":[],"data":["polySurface211",0,1,0,0]},{"id":32328,"path":"Assets\/Scenes\/Assets\/Prefabs\/howitzer.fbx","assetBundleId":-1,"components":[{"type":7,"id":33510,"data":[0,0,0,1,1,1,0,0,0,1]},{"type":11,"id":34290,"data":[12,34610]},{"type":13,"id":31726,"data":[null,null,1,14,34472,[14,34472],1,1,0,0,-1,-1,1,1,0,0,1,1]}],"children":[],"data":["polySurface212",0,1,0,0]},{"id":32326,"path":"Assets\/Scenes\/Assets\/Prefabs\/howitzer.fbx","assetBundleId":-1,"components":[{"type":7,"id":33512,"data":[0,0,0,1,1,1,0,0,0,1]},{"type":11,"id":33948,"data":[12,34688]},{"type":13,"id":32170,"data":[null,null,1,14,34472,[14,34472],1,1,0,0,-1,-1,1,1,0,0,1,1]}],"children":[],"data":["polySurface213",0,1,0,0]},{"id":32324,"path":"Assets\/Scenes\/Assets\/Prefabs\/howitzer.fbx","assetBundleId":-1,"components":[{"type":7,"id":33514,"data":[0,0,0,1,1,1,0,0,0,1]},{"type":11,"id":34298,"data":[12,34708]},{"type":13,"id":32154,"data":[null,null,1,14,34472,[14,34472],1,1,0,0,-1,-1,1,1,0,0,1,1]}],"children":[],"data":["polySurface214",0,1,0,0]},{"id":32322,"path":"Assets\/Scenes\/Assets\/Prefabs\/howitzer.fbx","assetBundleId":-1,"components":[{"type":7,"id":33516,"data":[0,0,0,1,1,1,0,0,0,1]},{"type":11,"id":34152,"data":[12,34810]},{"type":13,"id":32070,"data":[null,null,1,14,34472,[14,34472],1,1,0,0,-1,-1,1,1,0,0,1,1]}],"children":[],"data":["polySurface215",0,1,0,0]},{"id":32320,"path":"Assets\/Scenes\/Assets\/Prefabs\/howitzer.fbx","assetBundleId":-1,"components":[{"type":7,"id":33518,"data":[0,0,0,1,1,1,0,0,0,1]},{"type":11,"id":33952,"data":[12,34498]},{"type":13,"id":31632,"data":[null,null,1,14,34472,[14,34472],1,1,0,0,-1,-1,1,1,0,0,1,1]}],"children":[],"data":["polySurface216",0,1,0,0]},{"id":32318,"path":"Assets\/Scenes\/Assets\/Prefabs\/howitzer.fbx","assetBundleId":-1,"components":[{"type":7,"id":33520,"data":[0,0,0,1,1,1,0,0,0,1]},{"type":11,"id":34270,"data":[12,35016]},{"type":13,"id":32174,"data":[null,null,1,14,34472,[14,34472],1,1,0,0,-1,-1,1,1,0,0,1,1]}],"children":[],"data":["polySurface217",0,1,0,0]},{"id":32316,"path":"Assets\/Scenes\/Assets\/Prefabs\/howitzer.fbx","assetBundleId":-1,"components":[{"type":7,"id":33522,"data":[0,0,0,1,1,1,0,0,0,1]},{"type":11,"id":33972,"data":[12,34992]},{"type":13,"id":31966,"data":[null,null,1,14,34472,[14,34472],1,1,0,0,-1,-1,1,1,0,0,1,1]}],"children":[],"data":["polySurface218",0,1,0,0]},{"id":32314,"path":"Assets\/Scenes\/Assets\/Prefabs\/howitzer.fbx","assetBundleId":-1,"components":[{"type":7,"id":33524,"data":[0,0,0,1,1,1,0,0,0,1]},{"type":11,"id":34446,"data":[12,34502]},{"type":13,"id":31842,"data":[null,null,1,14,34472,[14,34472],1,1,0,0,-1,-1,1,1,0,0,1,1]}],"children":[],"data":["polySurface219",0,1,0,0]},{"id":32312,"path":"Assets\/Scenes\/Assets\/Prefabs\/howitzer.fbx","assetBundleId":-1,"components":[{"type":7,"id":33526,"data":[0,0,0,1,1,1,0,0,0,1]},{"type":11,"id":34272,"data":[12,34624]},{"type":13,"id":32030,"data":[null,null,1,14,34472,[14,34472],1,1,0,0,-1,-1,1,1,0,0,1,1]}],"children":[],"data":["polySurface220",0,1,0,0]},{"id":32310,"path":"Assets\/Scenes\/Assets\/Prefabs\/howitzer.fbx","assetBundleId":-1,"components":[{"type":7,"id":33528,"data":[0,0,0,1,1,1,0,0,0,1]},{"type":11,"id":34286,"data":[12,34538]},{"type":13,"id":31790,"data":[null,null,1,14,34472,[14,34472],1,1,0,0,-1,-1,1,1,0,0,1,1]}],"children":[],"data":["polySurface221",0,1,0,0]},{"id":32308,"path":"Assets\/Scenes\/Assets\/Prefabs\/howitzer.fbx","assetBundleId":-1,"components":[{"type":7,"id":33530,"data":[0,0,0,1,1,1,0,0,0,1]},{"type":11,"id":34382,"data":[12,34912]},{"type":13,"id":31982,"data":[null,null,1,14,34472,[14,34472],1,1,0,0,-1,-1,1,1,0,0,1,1]}],"children":[],"data":["polySurface222",0,1,0,0]},{"id":32306,"path":"Assets\/Scenes\/Assets\/Prefabs\/howitzer.fbx","assetBundleId":-1,"components":[{"type":7,"id":33532,"data":[0,0,0,1,1,1,0,0,0,1]},{"type":11,"id":34356,"data":[12,35012]},{"type":13,"id":31964,"data":[null,null,1,14,34472,[14,34472],1,1,0,0,-1,-1,1,1,0,0,1,1]}],"children":[],"data":["polySurface223",0,1,0,0]},{"id":32304,"path":"Assets\/Scenes\/Assets\/Prefabs\/howitzer.fbx","assetBundleId":-1,"components":[{"type":7,"id":33534,"data":[0,0,0,1,1,1,0,0,0,1]},{"type":11,"id":33992,"data":[12,34864]},{"type":13,"id":31858,"data":[null,null,1,14,34472,[14,34472],1,1,0,0,-1,-1,1,1,0,0,1,1]}],"children":[],"data":["polySurface224",0,1,0,0]},{"id":32302,"path":"Assets\/Scenes\/Assets\/Prefabs\/howitzer.fbx","assetBundleId":-1,"components":[{"type":7,"id":33536,"data":[0,0,0,1,1,1,0,0,0,1]},{"type":11,"id":34188,"data":[12,34562]},{"type":13,"id":31902,"data":[null,null,1,14,34472,[14,34472],1,1,0,0,-1,-1,1,1,0,0,1,1]}],"children":[],"data":["polySurface225",0,1,0,0]},{"id":32300,"path":"Assets\/Scenes\/Assets\/Prefabs\/howitzer.fbx","assetBundleId":-1,"components":[{"type":7,"id":33538,"data":[0,0,0,1,1,1,0,0,0,1]},{"type":11,"id":34358,"data":[12,34774]},{"type":13,"id":31776,"data":[null,null,1,14,34472,[14,34472],1,1,0,0,-1,-1,1,1,0,0,1,1]}],"children":[],"data":["polySurface226",0,1,0,0]},{"id":32298,"path":"Assets\/Scenes\/Assets\/Prefabs\/howitzer.fbx","assetBundleId":-1,"components":[{"type":7,"id":33540,"data":[0,0,0,1,1,1,0,0,0,1]},{"type":11,"id":33950,"data":[12,34918]},{"type":13,"id":32100,"data":[null,null,1,14,34472,[14,34472],1,1,0,0,-1,-1,1,1,0,0,1,1]}],"children":[],"data":["polySurface227",0,1,0,0]},{"id":32296,"path":"Assets\/Scenes\/Assets\/Prefabs\/howitzer.fbx","assetBundleId":-1,"components":[{"type":7,"id":33542,"data":[0,0,0,1,1,1,0,0,0,1]},{"type":11,"id":33912,"data":[12,34608]},{"type":13,"id":31650,"data":[null,null,1,14,34472,[14,34472],1,1,0,0,-1,-1,1,1,0,0,1,1]}],"children":[],"data":["polySurface228",0,1,0,0]},{"id":32294,"path":"Assets\/Scenes\/Assets\/Prefabs\/howitzer.fbx","assetBundleId":-1,"components":[{"type":7,"id":33544,"data":[0,0,0,1,1,1,0,0,0,1]},{"type":11,"id":34038,"data":[12,34642]},{"type":13,"id":32124,"data":[null,null,1,14,34472,[14,34472],1,1,0,0,-1,-1,1,1,0,0,1,1]}],"children":[],"data":["polySurface229",0,1,0,0]},{"id":32292,"path":"Assets\/Scenes\/Assets\/Prefabs\/howitzer.fbx","assetBundleId":-1,"components":[{"type":7,"id":33546,"data":[0,0,0,1,1,1,0,0,0,1]},{"type":11,"id":34126,"data":[12,34910]},{"type":13,"id":32080,"data":[null,null,1,14,34472,[14,34472],1,1,0,0,-1,-1,1,1,0,0,1,1]}],"children":[],"data":["polySurface230",0,1,0,0]},{"id":32290,"path":"Assets\/Scenes\/Assets\/Prefabs\/howitzer.fbx","assetBundleId":-1,"components":[{"type":7,"id":33548,"data":[0,0,0,1,1,1,0,0,0,1]},{"type":11,"id":34258,"data":[12,35002]},{"type":13,"id":31968,"data":[null,null,1,14,34472,[14,34472],1,1,0,0,-1,-1,1,1,0,0,1,1]}],"children":[],"data":["polySurface231",0,1,0,0]},{"id":32288,"path":"Assets\/Scenes\/Assets\/Prefabs\/howitzer.fbx","assetBundleId":-1,"components":[{"type":7,"id":33550,"data":[0,0,0,1,1,1,0,0,0,1]},{"type":11,"id":34012,"data":[12,35004]},{"type":13,"id":31886,"data":[null,null,1,14,34472,[14,34472],1,1,0,0,-1,-1,1,1,0,0,1,1]}],"children":[],"data":["polySurface232",0,1,0,0]},{"id":32286,"path":"Assets\/Scenes\/Assets\/Prefabs\/howitzer.fbx","assetBundleId":-1,"components":[{"type":7,"id":33552,"data":[0,0,0,1,1,1,0,0,0,1]},{"type":11,"id":34212,"data":[12,35000]},{"type":13,"id":32016,"data":[null,null,1,14,34472,[14,34472],1,1,0,0,-1,-1,1,1,0,0,1,1]}],"children":[],"data":["polySurface233",0,1,0,0]},{"id":32284,"path":"Assets\/Scenes\/Assets\/Prefabs\/howitzer.fbx","assetBundleId":-1,"components":[{"type":7,"id":33554,"data":[0,0,0,1,1,1,0,0,0,1]},{"type":11,"id":34262,"data":[12,35026]},{"type":13,"id":31980,"data":[null,null,1,14,34472,[14,34472],1,1,0,0,-1,-1,1,1,0,0,1,1]}],"children":[],"data":["polySurface234",0,1,0,0]},{"id":32282,"path":"Assets\/Scenes\/Assets\/Prefabs\/howitzer.fbx","assetBundleId":-1,"components":[{"type":7,"id":33556,"data":[0,0,0,1,1,1,0,0,0,1]},{"type":11,"id":34260,"data":[12,34852]},{"type":13,"id":31696,"data":[null,null,1,14,34472,[14,34472],1,1,0,0,-1,-1,1,1,0,0,1,1]}],"children":[],"data":["polySurface235",0,1,0,0]},{"id":32280,"path":"Assets\/Scenes\/Assets\/Prefabs\/howitzer.fbx","assetBundleId":-1,"components":[{"type":7,"id":33558,"data":[0,0,0,1,1,1,0,0,0,1]},{"type":11,"id":34302,"data":[12,34860]},{"type":13,"id":31852,"data":[null,null,1,14,34472,[14,34472],1,1,0,0,-1,-1,1,1,0,0,1,1]}],"children":[],"data":["polySurface236",0,1,0,0]},{"id":32278,"path":"Assets\/Scenes\/Assets\/Prefabs\/howitzer.fbx","assetBundleId":-1,"components":[{"type":7,"id":33560,"data":[0,0,0,1,1,1,0,0,0,1]},{"type":11,"id":34310,"data":[12,34686]},{"type":13,"id":31720,"data":[null,null,1,14,34472,[14,34472],1,1,0,0,-1,-1,1,1,0,0,1,1]}],"children":[],"data":["polySurface237",0,1,0,0]},{"id":32276,"path":"Assets\/Scenes\/Assets\/Prefabs\/howitzer.fbx","assetBundleId":-1,"components":[{"type":7,"id":33562,"data":[0,0,0,1,1,1,0,0,0,1]},{"type":11,"id":33966,"data":[12,34784]},{"type":13,"id":31676,"data":[null,null,1,14,34472,[14,34472],1,1,0,0,-1,-1,1,1,0,0,1,1]}],"children":[],"data":["polySurface238",0,1,0,0]},{"id":32274,"path":"Assets\/Scenes\/Assets\/Prefabs\/howitzer.fbx","assetBundleId":-1,"components":[{"type":7,"id":33564,"data":[0,0,0,1,1,1,0,0,0,1]},{"type":11,"id":33946,"data":[12,34576]},{"type":13,"id":31882,"data":[null,null,1,14,34472,[14,34472],1,1,0,0,-1,-1,1,1,0,0,1,1]}],"children":[],"data":["polySurface239",0,1,0,0]},{"id":32272,"path":"Assets\/Scenes\/Assets\/Prefabs\/howitzer.fbx","assetBundleId":-1,"components":[{"type":7,"id":33566,"data":[0,0,0,1,1,1,0,0,0,1]},{"type":11,"id":34140,"data":[12,34968]},{"type":13,"id":32120,"data":[null,null,1,14,34472,[14,34472],1,1,0,0,-1,-1,1,1,0,0,1,1]}],"children":[],"data":["polySurface240",0,1,0,0]},{"id":32270,"path":"Assets\/Scenes\/Assets\/Prefabs\/howitzer.fbx","assetBundleId":-1,"components":[{"type":7,"id":33568,"data":[0,0,0,1,1,1,0,0,0,1]},{"type":11,"id":34432,"data":[12,34630]},{"type":13,"id":31644,"data":[null,null,1,14,34472,[14,34472],1,1,0,0,-1,-1,1,1,0,0,1,1]}],"children":[],"data":["polySurface241",0,1,0,0]},{"id":32268,"path":"Assets\/Scenes\/Assets\/Prefabs\/howitzer.fbx","assetBundleId":-1,"components":[{"type":7,"id":33570,"data":[0,0,0,1,1,1,0,0,0,1]},{"type":11,"id":33932,"data":[12,34838]},{"type":13,"id":32054,"data":[null,null,1,14,34472,[14,34472],1,1,0,0,-1,-1,1,1,0,0,1,1]}],"children":[],"data":["polySurface242",0,1,0,0]},{"id":32266,"path":"Assets\/Scenes\/Assets\/Prefabs\/howitzer.fbx","assetBundleId":-1,"components":[{"type":7,"id":33572,"data":[0,0,0,1,1,1,0,0,0,1]},{"type":11,"id":34042,"data":[12,34904]},{"type":13,"id":31860,"data":[null,null,1,14,34472,[14,34472],1,1,0,0,-1,-1,1,1,0,0,1,1]}],"children":[],"data":["polySurface243",0,1,0,0]},{"id":32264,"path":"Assets\/Scenes\/Assets\/Prefabs\/howitzer.fbx","assetBundleId":-1,"components":[{"type":7,"id":33574,"data":[0,0,0,1,1,1,0,0,0,1]},{"type":11,"id":34014,"data":[12,34506]},{"type":13,"id":31658,"data":[null,null,1,14,34472,[14,34472],1,1,0,0,-1,-1,1,1,0,0,1,1]}],"children":[],"data":["polySurface244",0,1,0,0]},{"id":32262,"path":"Assets\/Scenes\/Assets\/Prefabs\/howitzer.fbx","assetBundleId":-1,"components":[{"type":7,"id":33576,"data":[0,0,0,1,1,1,0,0,0,1]},{"type":11,"id":34324,"data":[12,34980]},{"type":13,"id":31884,"data":[null,null,1,14,34472,[14,34472],1,1,0,0,-1,-1,1,1,0,0,1,1]}],"children":[],"data":["polySurface245",0,1,0,0]},{"id":32260,"path":"Assets\/Scenes\/Assets\/Prefabs\/howitzer.fbx","assetBundleId":-1,"components":[{"type":7,"id":33578,"data":[0,0,0,1,1,1,0,0,0,1]},{"type":11,"id":34444,"data":[12,34734]},{"type":13,"id":32024,"data":[null,null,1,14,34472,[14,34472],1,1,0,0,-1,-1,1,1,0,0,1,1]}],"children":[],"data":["polySurface246",0,1,0,0]},{"id":32258,"path":"Assets\/Scenes\/Assets\/Prefabs\/howitzer.fbx","assetBundleId":-1,"components":[{"type":7,"id":33580,"data":[0,0,0,1,1,1,0,0,0,1]},{"type":11,"id":34172,"data":[12,34514]},{"type":13,"id":31702,"data":[null,null,1,14,34472,[14,34472],1,1,0,0,-1,-1,1,1,0,0,1,1]}],"children":[],"data":["polySurface247",0,1,0,0]},{"id":32256,"path":"Assets\/Scenes\/Assets\/Prefabs\/howitzer.fbx","assetBundleId":-1,"components":[{"type":7,"id":33582,"data":[0,0,0,1,1,1,0,0,0,1]},{"type":11,"id":34074,"data":[12,34530]},{"type":13,"id":31666,"data":[null,null,1,14,34472,[14,34472],1,1,0,0,-1,-1,1,1,0,0,1,1]}],"children":[],"data":["polySurface248",0,1,0,0]},{"id":32254,"path":"Assets\/Scenes\/Assets\/Prefabs\/howitzer.fbx","assetBundleId":-1,"components":[{"type":7,"id":33584,"data":[0,0,0,1,1,1,0,0,0,1]},{"type":11,"id":34292,"data":[12,34704]},{"type":13,"id":31818,"data":[null,null,1,14,34472,[14,34472],1,1,0,0,-1,-1,1,1,0,0,1,1]}],"children":[],"data":["polySurface249",0,1,0,0]},{"id":32252,"path":"Assets\/Scenes\/Assets\/Prefabs\/howitzer.fbx","assetBundleId":-1,"components":[{"type":7,"id":33586,"data":[0,0,0,1,1,1,0,0,0,1]},{"type":11,"id":34308,"data":[12,34656]},{"type":13,"id":31728,"data":[null,null,1,14,34472,[14,34472],1,1,0,0,-1,-1,1,1,0,0,1,1]}],"children":[],"data":["polySurface250",0,1,0,0]},{"id":32250,"path":"Assets\/Scenes\/Assets\/Prefabs\/howitzer.fbx","assetBundleId":-1,"components":[{"type":7,"id":33588,"data":[0,0,0,1,1,1,0,0,0,1]},{"type":11,"id":34056,"data":[12,34826]},{"type":13,"id":31756,"data":[null,null,1,14,34472,[14,34472],1,1,0,0,-1,-1,1,1,0,0,1,1]}],"children":[],"data":["polySurface251",0,1,0,0]},{"id":32248,"path":"Assets\/Scenes\/Assets\/Prefabs\/howitzer.fbx","assetBundleId":-1,"components":[{"type":7,"id":33590,"data":[0,0,0,1,1,1,0,0,0,1]},{"type":11,"id":34430,"data":[12,34906]},{"type":13,"id":32060,"data":[null,null,1,14,34472,[14,34472],1,1,0,0,-1,-1,1,1,0,0,1,1]}],"children":[],"data":["polySurface252",0,1,0,0]},{"id":32246,"path":"Assets\/Scenes\/Assets\/Prefabs\/howitzer.fbx","assetBundleId":-1,"components":[{"type":7,"id":33592,"data":[0,0,0,1,1,1,0,0,0,1]},{"type":11,"id":34388,"data":[12,34490]},{"type":13,"id":31990,"data":[null,null,1,14,34472,[14,34472],1,1,0,0,-1,-1,1,1,0,0,1,1]}],"children":[],"data":["polySurface253",0,1,0,0]},{"id":32244,"path":"Assets\/Scenes\/Assets\/Prefabs\/howitzer.fbx","assetBundleId":-1,"components":[{"type":7,"id":33594,"data":[0,0,0,1,1,1,0,0,0,1]},{"type":11,"id":34314,"data":[12,34812]},{"type":13,"id":31958,"data":[null,null,1,14,34472,[14,34472],1,1,0,0,-1,-1,1,1,0,0,1,1]}],"children":[],"data":["polySurface254",0,1,0,0]},{"id":32242,"path":"Assets\/Scenes\/Assets\/Prefabs\/howitzer.fbx","assetBundleId":-1,"components":[{"type":7,"id":33596,"data":[0,0,0,1,1,1,0,0,0,1]},{"type":11,"id":34346,"data":[12,34626]},{"type":13,"id":31928,"data":[null,null,1,14,34472,[14,34472],1,1,0,0,-1,-1,1,1,0,0,1,1]}],"children":[],"data":["polySurface255",0,1,0,0]},{"id":32240,"path":"Assets\/Scenes\/Assets\/Prefabs\/howitzer.fbx","assetBundleId":-1,"components":[{"type":7,"id":33598,"data":[0,0,0,1,1,1,0,0,0,1]},{"type":11,"id":34362,"data":[12,34620]},{"type":13,"id":32106,"data":[null,null,1,14,34472,[14,34472],1,1,0,0,-1,-1,1,1,0,0,1,1]}],"children":[],"data":["polySurface256",0,1,0,0]},{"id":32238,"path":"Assets\/Scenes\/Assets\/Prefabs\/howitzer.fbx","assetBundleId":-1,"components":[{"type":7,"id":33600,"data":[0,0,0,1,1,1,0,0,0,1]},{"type":11,"id":34200,"data":[12,34872]},{"type":13,"id":32050,"data":[null,null,1,14,34472,[14,34472],1,1,0,0,-1,-1,1,1,0,0,1,1]}],"children":[],"data":["polySurface257",0,1,0,0]},{"id":32236,"path":"Assets\/Scenes\/Assets\/Prefabs\/howitzer.fbx","assetBundleId":-1,"components":[{"type":7,"id":33602,"data":[0,0,0,1,1,1,0,0,0,1]},{"type":11,"id":34340,"data":[12,34770]},{"type":13,"id":32132,"data":[null,null,1,14,34472,[14,34472],1,1,0,0,-1,-1,1,1,0,0,1,1]}],"children":[],"data":["polySurface258",0,1,0,0]},{"id":32234,"path":"Assets\/Scenes\/Assets\/Prefabs\/howitzer.fbx","assetBundleId":-1,"components":[{"type":7,"id":33604,"data":[0,0,0,1,1,1,0,0,0,1]},{"type":11,"id":34102,"data":[12,34994]},{"type":13,"id":31844,"data":[null,null,1,14,34472,[14,34472],1,1,0,0,-1,-1,1,1,0,0,1,1]}],"children":[],"data":["polySurface259",0,1,0,0]},{"id":32232,"path":"Assets\/Scenes\/Assets\/Prefabs\/howitzer.fbx","assetBundleId":-1,"components":[{"type":7,"id":33606,"data":[0,0,0,1,1,1,0,0,0,1]},{"type":11,"id":34008,"data":[12,34710]},{"type":13,"id":32026,"data":[null,null,1,14,34472,[14,34472],1,1,0,0,-1,-1,1,1,0,0,1,1]}],"children":[],"data":["polySurface260",0,1,0,0]},{"id":32230,"path":"Assets\/Scenes\/Assets\/Prefabs\/howitzer.fbx","assetBundleId":-1,"components":[{"type":7,"id":33608,"data":[0,0,0,1,1,1,0,0,0,1]},{"type":11,"id":34088,"data":[12,34612]},{"type":13,"id":31746,"data":[null,null,1,14,34472,[14,34472],1,1,0,0,-1,-1,1,1,0,0,1,1]}],"children":[],"data":["polySurface261",0,1,0,0]},{"id":32228,"path":"Assets\/Scenes\/Assets\/Prefabs\/howitzer.fbx","assetBundleId":-1,"components":[{"type":7,"id":33610,"data":[0,0,0,1,1,1,0,0,0,1]},{"type":11,"id":34384,"data":[12,34556]},{"type":13,"id":32034,"data":[null,null,1,14,34472,[14,34472],1,1,0,0,-1,-1,1,1,0,0,1,1]}],"children":[],"data":["polySurface262",0,1,0,0]},{"id":32226,"path":"Assets\/Scenes\/Assets\/Prefabs\/howitzer.fbx","assetBundleId":-1,"components":[{"type":7,"id":33612,"data":[0,0,0,1,1,1,0,0,0,1]},{"type":11,"id":34048,"data":[12,34726]},{"type":13,"id":31712,"data":[null,null,1,14,34472,[14,34472],1,1,0,0,-1,-1,1,1,0,0,1,1]}],"children":[],"data":["polySurface263",0,1,0,0]},{"id":32224,"path":"Assets\/Scenes\/Assets\/Prefabs\/howitzer.fbx","assetBundleId":-1,"components":[{"type":7,"id":33614,"data":[0,0,0,1,1,1,0,0,0,1]},{"type":11,"id":34026,"data":[12,34752]},{"type":13,"id":32110,"data":[null,null,1,14,34472,[14,34472],1,1,0,0,-1,-1,1,1,0,0,1,1]}],"children":[],"data":["polySurface264",0,1,0,0]},{"id":32222,"path":"Assets\/Scenes\/Assets\/Prefabs\/howitzer.fbx","assetBundleId":-1,"components":[{"type":7,"id":33616,"data":[0,0,0,1,1,1,0,0,0,1]},{"type":11,"id":34186,"data":[12,34678]},{"type":13,"id":31978,"data":[null,null,1,14,34472,[14,34472],1,1,0,0,-1,-1,1,1,0,0,1,1]}],"children":[],"data":["polySurface265",0,1,0,0]},{"id":32220,"path":"Assets\/Scenes\/Assets\/Prefabs\/howitzer.fbx","assetBundleId":-1,"components":[{"type":7,"id":33618,"data":[0,0,0,1,1,1,0,0,0,1]},{"type":11,"id":34278,"data":[12,34606]},{"type":13,"id":32002,"data":[null,null,1,14,34472,[14,34472],1,1,0,0,-1,-1,1,1,0,0,1,1]}],"children":[],"data":["polySurface266",0,1,0,0]},{"id":32218,"path":"Assets\/Scenes\/Assets\/Prefabs\/howitzer.fbx","assetBundleId":-1,"components":[{"type":7,"id":33620,"data":[0,0,0,1,1,1,0,0,0,1]},{"type":11,"id":34076,"data":[12,34508]},{"type":13,"id":32114,"data":[null,null,1,14,34472,[14,34472],1,1,0,0,-1,-1,1,1,0,0,1,1]}],"children":[],"data":["polySurface267",0,1,0,0]},{"id":32216,"path":"Assets\/Scenes\/Assets\/Prefabs\/howitzer.fbx","assetBundleId":-1,"components":[{"type":7,"id":33622,"data":[0,0,0,1,1,1,0,0,0,1]},{"type":11,"id":34352,"data":[12,34666]},{"type":13,"id":31772,"data":[null,null,1,14,34472,[14,34472],1,1,0,0,-1,-1,1,1,0,0,1,1]}],"children":[],"data":["polySurface268",0,1,0,0]},{"id":32214,"path":"Assets\/Scenes\/Assets\/Prefabs\/howitzer.fbx","assetBundleId":-1,"components":[{"type":7,"id":33624,"data":[0,0,0,1,1,1,0,0,0,1]},{"type":11,"id":34202,"data":[12,34756]},{"type":13,"id":32162,"data":[null,null,1,14,34472,[14,34472],1,1,0,0,-1,-1,1,1,0,0,1,1]}],"children":[],"data":["polySurface269",0,1,0,0]},{"id":32212,"path":"Assets\/Scenes\/Assets\/Prefabs\/howitzer.fbx","assetBundleId":-1,"components":[{"type":7,"id":33626,"data":[0,0,0,1,1,1,0,0,0,1]},{"type":11,"id":33958,"data":[12,34778]},{"type":13,"id":31880,"data":[null,null,1,14,34472,[14,34472],1,1,0,0,-1,-1,1,1,0,0,1,1]}],"children":[],"data":["polySurface270",0,1,0,0]},{"id":32210,"path":"Assets\/Scenes\/Assets\/Prefabs\/howitzer.fbx","assetBundleId":-1,"components":[{"type":7,"id":33628,"data":[0,0,0,1,1,1,0,0,0,1]},{"type":11,"id":33936,"data":[12,34732]},{"type":13,"id":31784,"data":[null,null,1,14,34472,[14,34472],1,1,0,0,-1,-1,1,1,0,0,1,1]}],"children":[],"data":["polySurface271",0,1,0,0]},{"id":32208,"path":"Assets\/Scenes\/Assets\/Prefabs\/howitzer.fbx","assetBundleId":-1,"components":[{"type":7,"id":33630,"data":[0,0,0,1,1,1,0,0,0,1]},{"type":11,"id":34062,"data":[12,34546]},{"type":13,"id":32184,"data":[null,null,1,14,34472,[14,34472],1,1,0,0,-1,-1,1,1,0,0,1,1]}],"children":[],"data":["polySurface272",0,1,0,0]},{"id":32206,"path":"Assets\/Scenes\/Assets\/Prefabs\/howitzer.fbx","assetBundleId":-1,"components":[{"type":7,"id":33632,"data":[0,0,0,1,1,1,0,0,0,1]},{"type":11,"id":34234,"data":[12,34894]},{"type":13,"id":32136,"data":[null,null,1,14,34472,[14,34472],1,1,0,0,-1,-1,1,1,0,0,1,1]}],"children":[],"data":["polySurface273",0,1,0,0]},{"id":32204,"path":"Assets\/Scenes\/Assets\/Prefabs\/howitzer.fbx","assetBundleId":-1,"components":[{"type":7,"id":33634,"data":[0,0,0,1,1,1,0,0,0,1]},{"type":11,"id":34386,"data":[12,34874]},{"type":13,"id":31710,"data":[null,null,1,14,34472,[14,34472],1,1,0,0,-1,-1,1,1,0,0,1,1]}],"children":[],"data":["polySurface278",0,1,0,0]},{"id":32202,"path":"Assets\/Scenes\/Assets\/Prefabs\/howitzer.fbx","assetBundleId":-1,"components":[{"type":7,"id":33636,"data":[0,0,0,1,1,1,0,0,0,1]},{"type":11,"id":33968,"data":[12,34858]},{"type":13,"id":31992,"data":[null,null,1,14,34472,[14,34472],1,1,0,0,-1,-1,1,1,0,0,1,1]}],"children":[],"data":["polySurface279",0,1,0,0]},{"id":32200,"path":"Assets\/Scenes\/Assets\/Prefabs\/howitzer.fbx","assetBundleId":-1,"components":[{"type":7,"id":33638,"data":[0,0,0,1,1,1,0,0,0,1]},{"type":11,"id":33914,"data":[12,34986]},{"type":13,"id":32058,"data":[null,null,1,14,34472,[14,34472],1,1,0,0,-1,-1,1,1,0,0,1,1]}],"children":[],"data":["polySurface280",0,1,0,0]},{"id":32198,"path":"Assets\/Scenes\/Assets\/Prefabs\/howitzer.fbx","assetBundleId":-1,"components":[{"type":7,"id":33640,"data":[0,0,0,1,1,1,0,0,0,1]},{"type":11,"id":34398,"data":[12,34832]},{"type":13,"id":31846,"data":[null,null,1,14,34472,[14,34472],1,1,0,0,-1,-1,1,1,0,0,1,1]}],"children":[],"data":["polySurface281",0,1,0,0]},{"id":32196,"path":"Assets\/Scenes\/Assets\/Prefabs\/howitzer.fbx","assetBundleId":-1,"components":[{"type":7,"id":33642,"data":[0,0,0,1,1,1,0,0,0,1]},{"type":11,"id":34006,"data":[12,34504]},{"type":13,"id":31898,"data":[null,null,1,14,34472,[14,34472],1,1,0,0,-1,-1,1,1,0,0,1,1]}],"children":[],"data":["polySurface282",0,1,0,0]},{"id":32194,"path":"Assets\/Scenes\/Assets\/Prefabs\/howitzer.fbx","assetBundleId":-1,"components":[{"type":7,"id":33644,"data":[0,0,0,1,1,1,0,0,0,1]},{"type":11,"id":34002,"data":[12,34924]},{"type":13,"id":31634,"data":[null,null,1,14,34472,[14,34472],1,1,0,0,-1,-1,1,1,0,0,1,1]}],"children":[],"data":["polySurface283",0,1,0,0]},{"id":32192,"path":"Assets\/Scenes\/Assets\/Prefabs\/howitzer.fbx","assetBundleId":-1,"components":[{"type":7,"id":33646,"data":[0,0,0,1,1,1,0,0,0,1]},{"type":11,"id":33964,"data":[12,34650]},{"type":13,"id":31668,"data":[null,null,1,14,31700,[14,31700],1,1,0,0,-1,-1,1,1,0,0,1,1]}],"children":[],"data":["polySurface284",0,1,0,0]},{"id":32190,"path":"Assets\/Scenes\/Assets\/Prefabs\/howitzer.fbx","assetBundleId":-1,"components":[{"type":7,"id":33648,"data":[0,0,0,1,1,1,0,0,0,1]},{"type":11,"id":34122,"data":[12,34850]},{"type":13,"id":32116,"data":[null,null,1,14,31700,[14,31700],1,1,0,0,-1,-1,1,1,0,0,1,1]}],"children":[],"data":["polySurface285",0,1,0,0]},{"id":32188,"path":"Assets\/Scenes\/Assets\/Prefabs\/howitzer.fbx","assetBundleId":-1,"components":[{"type":7,"id":33650,"data":[0,0,0,1,1,1,0,0,0,1]},{"type":11,"id":34134,"data":[12,34574]},{"type":13,"id":31856,"data":[null,null,1,14,31700,[14,31700],1,1,0,0,-1,-1,1,1,0,0,1,1]}],"children":[],"data":["polySurface286",0,1,0,0]},{"id":32186,"path":"Assets\/Scenes\/Assets\/Prefabs\/howitzer.fbx","assetBundleId":-1,"components":[{"type":7,"id":33652,"data":[0,0,0,1,1,1,0,0,0,1]},{"type":11,"id":33916,"data":[12,34740]},{"type":13,"id":32168,"data":[null,null,1,14,31700,[14,31700],1,1,0,0,-1,-1,1,1,0,0,1,1]}],"children":[],"data":["polySurface287",0,1,0,0]},{"id":32566,"path":"Assets\/Scenes\/Assets\/Prefabs\/howitzer.fbx","assetBundleId":-1,"components":[{"type":7,"id":33654,"data":[0,0,0,1,1,1,0,0,0,1]},{"type":11,"id":34070,"data":[12,34800]},{"type":13,"id":31972,"data":[null,null,1,14,31700,[14,31700],1,1,0,0,-1,-1,1,1,0,0,1,1]}],"children":[],"data":["polySurface302",0,1,0,0]},{"id":33874,"path":"Assets\/Scenes\/Assets\/Prefabs\/howitzer.fbx","assetBundleId":-1,"components":[{"type":7,"id":33656,"data":[0,0,0,1,1,1,0,0,0,1]},{"type":11,"id":34412,"data":[12,34892]},{"type":13,"id":31988,"data":[null,null,1,14,31700,[14,31700],1,1,0,0,-1,-1,1,1,0,0,1,1]}],"children":[],"data":["polySurface303",0,1,0,0]},{"id":32568,"path":"Assets\/Scenes\/Assets\/Prefabs\/howitzer.fbx","assetBundleId":-1,"components":[{"type":7,"id":33658,"data":[0,0,0,1,1,1,0,0,0,1]},{"type":11,"id":34010,"data":[12,34526]},{"type":13,"id":32022,"data":[null,null,1,14,31700,[14,31700],1,1,0,0,-1,-1,1,1,0,0,1,1]}],"children":[],"data":["polySurface304",0,1,0,0]},{"id":32570,"path":"Assets\/Scenes\/Assets\/Prefabs\/howitzer.fbx","assetBundleId":-1,"components":[{"type":7,"id":33660,"data":[0,0,0,1,1,1,0,0,0,1]},{"type":11,"id":34164,"data":[12,34938]},{"type":13,"id":32006,"data":[null,null,1,14,31700,[14,31700],1,1,0,0,-1,-1,1,1,0,0,1,1]}],"children":[],"data":["polySurface305",0,1,0,0]},{"id":32644,"path":"Assets\/Scenes\/Assets\/Prefabs\/howitzer.fbx","assetBundleId":-1,"components":[{"type":7,"id":33662,"data":[0,0,0,1,1,1,0,0,0,1]},{"type":11,"id":34116,"data":[12,34482]},{"type":13,"id":31878,"data":[null,null,1,14,31700,[14,31700],1,1,0,0,-1,-1,1,1,0,0,1,1]}],"children":[],"data":["polySurface306",0,1,0,0]},{"id":32572,"path":"Assets\/Scenes\/Assets\/Prefabs\/howitzer.fbx","assetBundleId":-1,"components":[{"type":7,"id":33664,"data":[0,0,0,1,1,1,0,0,0,1]},{"type":11,"id":34084,"data":[12,34934]},{"type":13,"id":31622,"data":[null,null,1,14,32046,[14,32046],1,1,0,0,-1,-1,1,1,0,0,1,1]}],"children":[],"data":["polySurface307",0,1,0,0]},{"id":32646,"path":"Assets\/Scenes\/Assets\/Prefabs\/howitzer.fbx","assetBundleId":-1,"components":[{"type":7,"id":33666,"data":[0,0,0,1,1,1,0,0,0,1]},{"type":11,"id":34162,"data":[12,34884]},{"type":13,"id":31736,"data":[null,null,1,14,32046,[14,32046],1,1,0,0,-1,-1,1,1,0,0,1,1]}],"children":[],"data":["polySurface308",0,1,0,0]},{"id":32574,"path":"Assets\/Scenes\/Assets\/Prefabs\/howitzer.fbx","assetBundleId":-1,"components":[{"type":7,"id":33668,"data":[0,0,0,1,1,1,0,0,0,1]},{"type":11,"id":34438,"data":[12,34956]},{"type":13,"id":32090,"data":[null,null,1,14,32046,[14,32046],1,1,0,0,-1,-1,1,1,0,0,1,1]}],"children":[],"data":["polySurface309",0,1,0,0]},{"id":32576,"path":"Assets\/Scenes\/Assets\/Prefabs\/howitzer.fbx","assetBundleId":-1,"components":[{"type":7,"id":33670,"data":[0,0,0,1,1,1,0,0,0,1]},{"type":11,"id":34458,"data":[12,34972]},{"type":13,"id":31834,"data":[null,null,1,14,32046,[14,32046],1,1,0,0,-1,-1,1,1,0,0,1,1]}],"children":[],"data":["polySurface310",0,1,0,0]},{"id":32648,"path":"Assets\/Scenes\/Assets\/Prefabs\/howitzer.fbx","assetBundleId":-1,"components":[{"type":7,"id":33672,"data":[0,0,0,1,1,1,0,0,0,1]},{"type":11,"id":34396,"data":[12,34836]},{"type":13,"id":32032,"data":[null,null,1,14,32046,[14,32046],1,1,0,0,-1,-1,1,1,0,0,1,1]}],"children":[],"data":["polySurface311",0,1,0,0]},{"id":32578,"path":"Assets\/Scenes\/Assets\/Prefabs\/howitzer.fbx","assetBundleId":-1,"components":[{"type":7,"id":33674,"data":[0,0,0,1,1,1,0,0,0,1]},{"type":11,"id":34206,"data":[12,34804]},{"type":13,"id":32020,"data":[null,null,1,14,32046,[14,32046],1,1,0,0,-1,-1,1,1,0,0,1,1]}],"children":[],"data":["polySurface312",0,1,0,0]},{"id":32580,"path":"Assets\/Scenes\/Assets\/Prefabs\/howitzer.fbx","assetBundleId":-1,"components":[{"type":7,"id":33676,"data":[0,0,0,1,1,1,0,0,0,1]},{"type":11,"id":34224,"data":[12,34940]},{"type":13,"id":32140,"data":[null,null,1,14,32046,[14,32046],1,1,0,0,-1,-1,1,1,0,0,1,1]}],"children":[],"data":["polySurface313",0,1,0,0]},{"id":32582,"path":"Assets\/Scenes\/Assets\/Prefabs\/howitzer.fbx","assetBundleId":-1,"components":[{"type":7,"id":33678,"data":[0,0,0,1,1,1,0,0,0,1]},{"type":11,"id":33976,"data":[12,34750]},{"type":13,"id":31872,"data":[null,null,1,14,34472,[14,34472],1,1,0,0,-1,-1,1,1,0,0,1,1]}],"children":[],"data":["polySurface323",0,1,0,0]},{"id":32584,"path":"Assets\/Scenes\/Assets\/Prefabs\/howitzer.fbx","assetBundleId":-1,"components":[{"type":7,"id":33680,"data":[0,0,0,1,1,1,0,0,0,1]},{"type":11,"id":34448,"data":[12,34558]},{"type":13,"id":31778,"data":[null,null,1,14,34472,[14,34472],1,1,0,0,-1,-1,1,1,0,0,1,1]}],"children":[],"data":["polySurface324",0,1,0,0]},{"id":32586,"path":"Assets\/Scenes\/Assets\/Prefabs\/howitzer.fbx","assetBundleId":-1,"components":[{"type":7,"id":33682,"data":[0,0,0,1,1,1,0,0,0,1]},{"type":11,"id":34080,"data":[12,34758]},{"type":13,"id":31664,"data":[null,null,1,14,31624,[14,31624],1,1,0,0,-1,-1,1,1,0,0,1,1]}],"children":[],"data":["polySurface326",0,1,0,0]},{"id":33882,"path":"Assets\/Scenes\/Assets\/Prefabs\/howitzer.fbx","assetBundleId":-1,"components":[{"type":7,"id":33684,"data":[0,0,0,1,1,1,0,0,0,1]},{"type":11,"id":33954,"data":[12,34680]},{"type":13,"id":31808,"data":[null,null,1,14,31700,[14,31700],1,1,0,0,-1,-1,1,1,0,0,1,1]}],"children":[],"data":["polySurface327",0,1,0,0]},{"id":32588,"path":"Assets\/Scenes\/Assets\/Prefabs\/howitzer.fbx","assetBundleId":-1,"components":[{"type":7,"id":33686,"data":[0,0,0,1,1,1,0,0,0,1]},{"type":11,"id":34240,"data":[12,34614]},{"type":13,"id":32172,"data":[null,null,1,14,31700,[14,31700],1,1,0,0,-1,-1,1,1,0,0,1,1]}],"children":[],"data":["polySurface333",0,1,0,0]},{"id":32590,"path":"Assets\/Scenes\/Assets\/Prefabs\/howitzer.fbx","assetBundleId":-1,"components":[{"type":7,"id":33688,"data":[0,0,0,1,1,1,0,0,0,1]},{"type":11,"id":34110,"data":[12,34600]},{"type":13,"id":31826,"data":[null,null,1,14,31700,[14,31700],1,1,0,0,-1,-1,1,1,0,0,1,1]}],"children":[],"data":["polySurface334",0,1,0,0]},{"id":33888,"path":"Assets\/Scenes\/Assets\/Prefabs\/howitzer.fbx","assetBundleId":-1,"components":[{"type":7,"id":33690,"data":[0,0,0,1,1,1,0,0,0,1]},{"type":11,"id":34342,"data":[12,34820]},{"type":13,"id":31906,"data":[null,null,1,14,31700,[14,31700],1,1,0,0,-1,-1,1,1,0,0,1,1]}],"children":[],"data":["polySurface335",0,1,0,0]},{"id":32592,"path":"Assets\/Scenes\/Assets\/Prefabs\/howitzer.fbx","assetBundleId":-1,"components":[{"type":7,"id":33692,"data":[0,0,0,1,1,1,0,0,0,1]},{"type":11,"id":34016,"data":[12,34960]},{"type":13,"id":31946,"data":[null,null,1,14,31700,[14,31700],1,1,0,0,-1,-1,1,1,0,0,1,1]}],"children":[],"data":["polySurface336",0,1,0,0]},{"id":32594,"path":"Assets\/Scenes\/Assets\/Prefabs\/howitzer.fbx","assetBundleId":-1,"components":[{"type":7,"id":33694,"data":[0,0,0,1,1,1,0,0,0,1]},{"type":11,"id":34210,"data":[12,34762]},{"type":13,"id":31674,"data":[null,null,1,14,31624,[14,31624],1,1,0,0,-1,-1,1,1,0,0,1,1]}],"children":[],"data":["polySurface337",0,1,0,0]},{"id":33842,"path":"Assets\/Scenes\/Assets\/Prefabs\/howitzer.fbx","assetBundleId":-1,"components":[{"type":7,"id":33696,"data":[0,0,0,1,1,1,0,0,0,1]},{"type":11,"id":34178,"data":[12,34492]},{"type":13,"id":32042,"data":[null,null,1,14,31624,[14,31624],1,1,0,0,-1,-1,1,1,0,0,1,1]}],"children":[],"data":["polySurface338",0,1,0,0]},{"id":32596,"path":"Assets\/Scenes\/Assets\/Prefabs\/howitzer.fbx","assetBundleId":-1,"components":[{"type":7,"id":33698,"data":[0,0,0,1,1,1,0,0,0,1]},{"type":11,"id":34336,"data":[12,34886]},{"type":13,"id":31984,"data":[null,null,1,14,31700,[14,31700],1,1,0,0,-1,-1,1,1,0,0,1,1]}],"children":[],"data":["polySurface349",0,1,0,0]},{"id":33884,"path":"Assets\/Scenes\/Assets\/Prefabs\/howitzer.fbx","assetBundleId":-1,"components":[{"type":7,"id":33700,"data":[0,0,0,1,1,1,0,0,0,1]},{"type":11,"id":34404,"data":[12,34670]},{"type":13,"id":31718,"data":[null,null,1,14,31700,[14,31700],1,1,0,0,-1,-1,1,1,0,0,1,1]}],"children":[],"data":["polySurface350",0,1,0,0]},{"id":32598,"path":"Assets\/Scenes\/Assets\/Prefabs\/howitzer.fbx","assetBundleId":-1,"components":[{"type":7,"id":33702,"data":[0,0,0,1,1,1,0,0,0,1]},{"type":11,"id":33922,"data":[12,34962]},{"type":13,"id":31892,"data":[null,null,1,14,31700,[14,31700],1,1,0,0,-1,-1,1,1,0,0,1,1]}],"children":[],"data":["polySurface351",0,1,0,0]},{"id":32600,"path":"Assets\/Scenes\/Assets\/Prefabs\/howitzer.fbx","assetBundleId":-1,"components":[{"type":7,"id":33704,"data":[0,0,0,1,1,1,0,0,0,1]},{"type":11,"id":34180,"data":[12,34528]},{"type":13,"id":31738,"data":[null,null,1,14,31700,[14,31700],1,1,0,0,-1,-1,1,1,0,0,1,1]}],"children":[],"data":["polySurface352",0,1,0,0]},{"id":32602,"path":"Assets\/Scenes\/Assets\/Prefabs\/howitzer.fbx","assetBundleId":-1,"components":[{"type":7,"id":33706,"data":[0,0,0,1,1,1,0,0,0,1]},{"type":11,"id":34230,"data":[12,34722]},{"type":13,"id":32166,"data":[null,null,1,14,31700,[14,31700],1,1,0,0,-1,-1,1,1,0,0,1,1]}],"children":[],"data":["polySurface353",0,1,0,0]},{"id":32604,"path":"Assets\/Scenes\/Assets\/Prefabs\/howitzer.fbx","assetBundleId":-1,"components":[{"type":7,"id":33708,"data":[0,0,0,1,1,1,0,0,0,1]},{"type":11,"id":34058,"data":[12,34844]},{"type":13,"id":32008,"data":[null,null,1,14,31700,[14,31700],1,1,0,0,-1,-1,1,1,0,0,1,1]}],"children":[],"data":["polySurface354",0,1,0,0]},{"id":32606,"path":"Assets\/Scenes\/Assets\/Prefabs\/howitzer.fbx","assetBundleId":-1,"components":[{"type":7,"id":33710,"data":[0,0,0,1,1,1,0,0,0,1]},{"type":11,"id":34392,"data":[12,34662]},{"type":13,"id":32064,"data":[null,null,1,14,31700,[14,31700],1,1,0,0,-1,-1,1,1,0,0,1,1]}],"children":[],"data":["polySurface355",0,1,0,0]},{"id":32608,"path":"Assets\/Scenes\/Assets\/Prefabs\/howitzer.fbx","assetBundleId":-1,"components":[{"type":7,"id":33712,"data":[0,0,0,1,1,1,0,0,0,1]},{"type":11,"id":34366,"data":[12,34786]},{"type":13,"id":32144,"data":[null,null,1,14,34472,[14,34472],1,1,0,0,-1,-1,1,1,0,0,1,1]}],"children":[],"data":["polySurface357",0,1,0,0]},{"id":33880,"path":"Assets\/Scenes\/Assets\/Prefabs\/howitzer.fbx","assetBundleId":-1,"components":[{"type":7,"id":33714,"data":[0,0,0,1,1,1,0,0,0,1]},{"type":11,"id":34018,"data":[12,34744]},{"type":13,"id":32096,"data":[null,null,1,14,34856,[14,34856],1,1,0,0,-1,-1,1,1,0,0,1,1]}],"children":[],"data":["polySurface358",0,1,0,0]},{"id":33898,"path":"Assets\/Scenes\/Assets\/Prefabs\/howitzer.fbx","assetBundleId":-1,"components":[{"type":7,"id":33716,"data":[0,0,0,1,1,1,0,0,0,1]},{"type":11,"id":34108,"data":[12,34552]},{"type":13,"id":31692,"data":[null,null,1,14,34524,[14,34524],1,1,0,0,-1,-1,1,1,0,0,1,1]}],"children":[],"data":["polySurface359",0,1,0,0]},{"id":33832,"path":"Assets\/Scenes\/Assets\/Prefabs\/howitzer.fbx","assetBundleId":-1,"components":[{"type":7,"id":33718,"data":[0,0,0,1,1,1,0,0,0,1]},{"type":11,"id":34318,"data":[12,35020]},{"type":13,"id":31940,"data":[null,null,1,14,34746,[14,34746],1,1,0,0,-1,-1,1,1,0,0,1,1]}],"children":[],"data":["polySurface360",0,1,0,0]},{"id":33850,"path":"Assets\/Scenes\/Assets\/Prefabs\/howitzer.fbx","assetBundleId":-1,"components":[{"type":7,"id":33720,"data":[0,0,0,1,1,1,0,0,0,1]},{"type":11,"id":34220,"data":[12,34466]},{"type":13,"id":32018,"data":[null,null,1,14,32046,[14,32046],1,1,0,0,-1,-1,1,1,0,0,1,1]}],"children":[],"data":["polySurface369",0,1,0,0]},{"id":33868,"path":"Assets\/Scenes\/Assets\/Prefabs\/howitzer.fbx","assetBundleId":-1,"components":[{"type":7,"id":33722,"data":[0,0,0,1,1,1,0,0,0,1]},{"type":11,"id":33928,"data":[12,35036]},{"type":13,"id":31748,"data":[null,null,1,14,31700,[14,31700],1,1,0,0,-1,-1,1,1,0,0,1,1]}],"children":[],"data":["polySurface373",0,1,0,0]},{"id":33872,"path":"Assets\/Scenes\/Assets\/Prefabs\/howitzer.fbx","assetBundleId":-1,"components":[{"type":7,"id":33724,"data":[0,0,0,1,1,1,0,0,0,1]},{"type":11,"id":34380,"data":[12,34724]},{"type":13,"id":31636,"data":[null,null,1,14,32046,[14,32046],1,1,0,0,-1,-1,1,1,0,0,1,1]}],"children":[],"data":["polySurface374",0,1,0,0]},{"id":33902,"path":"Assets\/Scenes\/Assets\/Prefabs\/howitzer.fbx","assetBundleId":-1,"components":[{"type":7,"id":33726,"data":[0,0,0,1,1,1,0,0,0,1]},{"type":11,"id":34244,"data":[12,34782]},{"type":13,"id":32000,"data":[null,null,1,14,31700,[14,31700],1,1,0,0,-1,-1,1,1,0,0,1,1]}],"children":[],"data":["polySurface376",0,1,0,0]},{"id":32612,"path":"Assets\/Scenes\/Assets\/Prefabs\/howitzer.fbx","assetBundleId":-1,"components":[{"type":7,"id":33728,"data":[0,0,0,1,1,1,0,0,0,1]},{"type":11,"id":34046,"data":[12,34668]},{"type":13,"id":31910,"data":[null,null,1,14,31700,[14,31700],1,1,0,0,-1,-1,1,1,0,0,1,1]}],"children":[],"data":["polySurface377",0,1,0,0]},{"id":32616,"path":"Assets\/Scenes\/Assets\/Prefabs\/howitzer.fbx","assetBundleId":-1,"components":[{"type":7,"id":33730,"data":[0,0,0,1,1,1,0,0,0,1]},{"type":11,"id":34276,"data":[12,34854]},{"type":13,"id":31934,"data":[null,null,1,14,32046,[14,32046],1,1,0,0,-1,-1,1,1,0,0,1,1]}],"children":[],"data":["polySurface378",0,1,0,0]},{"id":32610,"path":"Assets\/Scenes\/Assets\/Prefabs\/howitzer.fbx","assetBundleId":-1,"components":[{"type":7,"id":33732,"data":[0,0,0,1,1,1,0,0,0,1]},{"type":11,"id":34334,"data":[12,34690]},{"type":13,"id":31706,"data":[null,null,1,14,32046,[14,32046],1,1,0,0,-1,-1,1,1,0,0,1,1]}],"children":[],"data":["polySurface379",0,1,0,0]},{"id":32642,"path":"Assets\/Scenes\/Assets\/Prefabs\/howitzer.fbx","assetBundleId":-1,"components":[{"type":7,"id":33734,"data":[0,0,0,1,1,1,0,0,0,1]},{"type":11,"id":34368,"data":[12,34928]},{"type":13,"id":31942,"data":[null,null,1,14,32128,[14,32128],1,1,0,0,-1,-1,1,1,0,0,1,1]}],"children":[],"data":["polySurface382",0,1,0,0]},{"id":33900,"path":"Assets\/Scenes\/Assets\/Prefabs\/howitzer.fbx","assetBundleId":-1,"components":[{"type":7,"id":33736,"data":[0,0,0,1,1,1,0,0,0,1]},{"type":11,"id":34100,"data":[12,34754]},{"type":13,"id":32076,"data":[null,null,1,14,34748,[14,34748],1,1,0,0,-1,-1,1,1,0,0,1,1]}],"children":[],"data":["polySurface429",0,1,0,0]},{"id":32618,"path":"Assets\/Scenes\/Assets\/Prefabs\/howitzer.fbx","assetBundleId":-1,"components":[{"type":7,"id":33738,"data":[0,0,0,1,1,1,0,0,0,1]},{"type":11,"id":33934,"data":[12,35034]},{"type":13,"id":31832,"data":[null,null,1,14,31700,[14,31700],1,1,0,0,-1,-1,1,1,0,0,1,1]}],"children":[],"data":["polySurface431",0,1,0,0]},{"id":33894,"path":"Assets\/Scenes\/Assets\/Prefabs\/howitzer.fbx","assetBundleId":-1,"components":[{"type":7,"id":33740,"data":[0,0,0,1,1,1,0,0,0,1]},{"type":11,"id":34184,"data":[12,34952]},{"type":13,"id":32052,"data":[null,null,1,14,31624,[14,31624],1,1,0,0,-1,-1,1,1,0,0,1,1]}],"children":[],"data":["polySurface432",0,1,0,0]},{"id":32620,"path":"Assets\/Scenes\/Assets\/Prefabs\/howitzer.fbx","assetBundleId":-1,"components":[{"type":7,"id":33742,"data":[0,0,0,1,1,1,0,0,0,1]},{"type":11,"id":34044,"data":[12,34462]},{"type":13,"id":31820,"data":[null,null,1,14,31700,[14,31700],1,1,0,0,-1,-1,1,1,0,0,1,1]}],"children":[],"data":["polySurface433",0,1,0,0]},{"id":32622,"path":"Assets\/Scenes\/Assets\/Prefabs\/howitzer.fbx","assetBundleId":-1,"components":[{"type":7,"id":33744,"data":[0,0,0,1,1,1,0,0,0,1]},{"type":11,"id":34098,"data":[12,34978]},{"type":13,"id":31888,"data":[null,null,1,14,32046,[14,32046],1,1,0,0,-1,-1,1,1,0,0,1,1]}],"children":[],"data":["polySurface434",0,1,0,0]},{"id":32614,"path":"Assets\/Scenes\/Assets\/Prefabs\/howitzer.fbx","assetBundleId":-1,"components":[{"type":7,"id":33746,"data":[0,0,0,1,1,1,0,0,0,1]},{"type":11,"id":34402,"data":[12,34944]},{"type":13,"id":31794,"data":[null,null,1,14,32046,[14,32046],1,1,0,0,-1,-1,1,1,0,0,1,1]}],"children":[],"data":["polySurface435",0,1,0,0]},{"id":32624,"path":"Assets\/Scenes\/Assets\/Prefabs\/howitzer.fbx","assetBundleId":-1,"components":[{"type":7,"id":33748,"data":[0,0,0,1,1,1,0,0,0,1]},{"type":11,"id":34228,"data":[12,34694]},{"type":13,"id":31758,"data":[null,null,1,14,31624,[14,31624],1,1,0,0,-1,-1,1,1,0,0,1,1]}],"children":[],"data":["polySurface436",0,1,0,0]},{"id":33858,"path":"Assets\/Scenes\/Assets\/Prefabs\/howitzer.fbx","assetBundleId":-1,"components":[{"type":7,"id":33750,"data":[0,0,0,1,1,1,0,0,0,1]},{"type":11,"id":34460,"data":[12,34696]},{"type":13,"id":32098,"data":[null,null,1,14,32046,[14,32046],1,1,0,0,-1,-1,1,1,0,0,1,1]}],"children":[],"data":["polySurface437",0,1,0,0]},{"id":33836,"path":"Assets\/Scenes\/Assets\/Prefabs\/howitzer.fbx","assetBundleId":-1,"components":[{"type":7,"id":33752,"data":[0,0,0,1,1,1,0,0,0,1]},{"type":11,"id":34174,"data":[12,34890]},{"type":13,"id":32072,"data":[null,null,1,14,31700,[14,31700],1,1,0,0,-1,-1,1,1,0,0,1,1]}],"children":[],"data":["polySurface438",0,1,0,0]},{"id":32626,"path":"Assets\/Scenes\/Assets\/Prefabs\/howitzer.fbx","assetBundleId":-1,"components":[{"type":7,"id":33754,"data":[0,0,0,1,1,1,0,0,0,1]},{"type":11,"id":34348,"data":[12,34654]},{"type":13,"id":32066,"data":[null,null,1,14,31700,[14,31700],1,1,0,0,-1,-1,1,1,0,0,1,1]}],"children":[],"data":["polySurface439",0,1,0,0]},{"id":32650,"path":"Assets\/Scenes\/Assets\/Prefabs\/howitzer.fbx","assetBundleId":-1,"components":[{"type":7,"id":33756,"data":[0,0,0,1,1,1,0,0,0,1]},{"type":11,"id":33978,"data":[12,34622]},{"type":13,"id":31918,"data":[null,null,1,14,32046,[14,32046],1,1,0,0,-1,-1,1,1,0,0,1,1]}],"children":[],"data":["polySurface440",0,1,0,0]},{"id":33840,"path":"Assets\/Scenes\/Assets\/Prefabs\/howitzer.fbx","assetBundleId":-1,"components":[{"type":7,"id":33758,"data":[0,0,0,1,1,1,0,0,0,1]},{"type":11,"id":34208,"data":[12,35030]},{"type":13,"id":31770,"data":[null,null,1,14,31624,[14,31624],1,1,0,0,-1,-1,1,1,0,0,1,1]}],"children":[],"data":["polySurface444",0,1,0,0]},{"id":33828,"path":"Assets\/Scenes\/Assets\/Prefabs\/howitzer.fbx","assetBundleId":-1,"components":[{"type":7,"id":33760,"data":[0,0,0,1,1,1,0,0,0,1]},{"type":11,"id":34072,"data":[12,34760]},{"type":13,"id":32158,"data":[null,null,1,14,31700,[14,31700],1,1,0,0,-1,-1,1,1,0,0,1,1]}],"children":[],"data":["polySurface445",0,1,0,0]},{"id":33856,"path":"Assets\/Scenes\/Assets\/Prefabs\/howitzer.fbx","assetBundleId":-1,"components":[{"type":7,"id":33762,"data":[0,0,0,1,1,1,0,0,0,1]},{"type":11,"id":34338,"data":[12,34772]},{"type":13,"id":31994,"data":[null,null,1,14,32046,[14,32046],1,1,0,0,-1,-1,1,1,0,0,1,1]}],"children":[],"data":["polySurface446",0,1,0,0]},{"id":32628,"path":"Assets\/Scenes\/Assets\/Prefabs\/howitzer.fbx","assetBundleId":-1,"components":[{"type":7,"id":33764,"data":[0,0,0,1,1,1,0,0,0,1]},{"type":11,"id":34416,"data":[12,34764]},{"type":13,"id":31894,"data":[null,null,1,14,32046,[14,32046],1,1,0,0,-1,-1,1,1,0,0,1,1]}],"children":[],"data":["polySurface448",0,1,0,0]},{"id":32630,"path":"Assets\/Scenes\/Assets\/Prefabs\/howitzer.fbx","assetBundleId":-1,"components":[{"type":7,"id":33766,"data":[0,0,0,1,1,1,0,0,0,1]},{"type":11,"id":34350,"data":[12,34486]},{"type":13,"id":31914,"data":[null,null,1,14,32046,[14,32046],1,1,0,0,-1,-1,1,1,0,0,1,1]}],"children":[],"data":["polySurface449",0,1,0,0]},{"id":33870,"path":"Assets\/Scenes\/Assets\/Prefabs\/howitzer.fbx","assetBundleId":-1,"components":[{"type":7,"id":33768,"data":[0,0,0,1,1,1,0,0,0,1]},{"type":11,"id":34114,"data":[12,34930]},{"type":13,"id":31652,"data":[null,null,1,14,32046,[14,32046],1,1,0,0,-1,-1,1,1,0,0,1,1]}],"children":[],"data":["polySurface450",0,1,0,0]},{"id":32632,"path":"Assets\/Scenes\/Assets\/Prefabs\/howitzer.fbx","assetBundleId":-1,"components":[{"type":7,"id":33770,"data":[0,0,0,1,1,1,0,0,0,1]},{"type":11,"id":34138,"data":[12,34954]},{"type":13,"id":31814,"data":[null,null,1,14,31624,[14,31624],1,1,0,0,-1,-1,1,1,0,0,1,1]}],"children":[],"data":["polySurface452",0,1,0,0]},{"id":33830,"path":"Assets\/Scenes\/Assets\/Prefabs\/howitzer.fbx","assetBundleId":-1,"components":[{"type":7,"id":33772,"data":[0,0,0,1,1,1,0,0,0,1]},{"type":11,"id":34204,"data":[12,34468]},{"type":13,"id":32082,"data":[null,null,1,14,31700,[14,31700],1,1,0,0,-1,-1,1,1,0,0,1,1]}],"children":[],"data":["polySurface453",0,1,0,0]},{"id":33848,"path":"Assets\/Scenes\/Assets\/Prefabs\/howitzer.fbx","assetBundleId":-1,"components":[{"type":7,"id":33774,"data":[0,0,0,1,1,1,0,0,0,1]},{"type":11,"id":34360,"data":[12,34966]},{"type":13,"id":31662,"data":[null,null,1,14,32128,[14,32128],1,1,0,0,-1,-1,1,1,0,0,1,1]}],"children":[],"data":["polySurface454",0,1,0,0]},{"id":33838,"path":"Assets\/Scenes\/Assets\/Prefabs\/howitzer.fbx","assetBundleId":-1,"components":[{"type":7,"id":33776,"data":[0,0,0,1,1,1,0,0,0,1]},{"type":11,"id":34266,"data":[12,34946]},{"type":13,"id":31716,"data":[null,null,1,14,31700,[14,31700],1,1,0,0,-1,-1,1,1,0,0,1,1]}],"children":[],"data":["polySurface455",0,1,0,0]},{"id":33896,"path":"Assets\/Scenes\/Assets\/Prefabs\/howitzer.fbx","assetBundleId":-1,"components":[{"type":7,"id":33778,"data":[0,0,0,1,1,1,0,0,0,1]},{"type":11,"id":34304,"data":[12,35008]},{"type":13,"id":31786,"data":[null,null,1,14,31624,[14,31624],1,1,0,0,-1,-1,1,1,0,0,1,1]}],"children":[],"data":["polySurface457",0,1,0,0]},{"id":33904,"path":"Assets\/Scenes\/Assets\/Prefabs\/howitzer.fbx","assetBundleId":-1,"components":[{"type":7,"id":33780,"data":[0,0,0,1,1,1,0,0,0,1]},{"type":11,"id":34264,"data":[12,34888]},{"type":13,"id":31722,"data":[null,null,1,14,31624,[14,31624],1,1,0,0,-1,-1,1,1,0,0,1,1]}],"children":[],"data":["polySurface461",0,1,0,0]},{"id":33860,"path":"Assets\/Scenes\/Assets\/Prefabs\/howitzer.fbx","assetBundleId":-1,"components":[{"type":7,"id":33782,"data":[0,0,0,1,1,1,0,0,0,1]},{"type":11,"id":34408,"data":[12,34540]},{"type":13,"id":31766,"data":[null,null,1,14,34602,[14,34602],1,1,0,0,-1,-1,1,1,0,0,1,1]}],"children":[],"data":["polySurface462",0,1,0,0]},{"id":33862,"path":"Assets\/Scenes\/Assets\/Prefabs\/howitzer.fbx","assetBundleId":-1,"components":[{"type":7,"id":33784,"data":[0,0,0,1,1,1,0,0,0,1]},{"type":11,"id":34214,"data":[12,35032]},{"type":13,"id":32178,"data":[null,null,1,14,35024,[14,35024],1,1,0,0,-1,-1,1,1,0,0,1,1]}],"children":[],"data":["polySurface464",0,1,0,0]},{"id":33844,"path":"Assets\/Scenes\/Assets\/Prefabs\/howitzer.fbx","assetBundleId":-1,"components":[{"type":7,"id":33786,"data":[0,0,0,1,1,1,0,0,0,1]},{"type":11,"id":33926,"data":[12,34896]},{"type":13,"id":31900,"data":[null,null,1,14,34684,[14,34684],1,1,0,0,-1,-1,1,1,0,0,1,1]}],"children":[],"data":["polySurface465",0,1,0,0]},{"id":33822,"path":"Assets\/Scenes\/Assets\/Prefabs\/howitzer.fbx","assetBundleId":-1,"components":[{"type":7,"id":33788,"data":[0,0,0,1,1,1,0,0,0,1]},{"type":11,"id":34232,"data":[12,34974]},{"type":13,"id":31698,"data":[null,null,1,14,34534,[14,34534],1,1,0,0,-1,-1,1,1,0,0,1,1]}],"children":[],"data":["polySurface466",0,1,0,0]},{"id":33890,"path":"Assets\/Scenes\/Assets\/Prefabs\/howitzer.fbx","assetBundleId":-1,"components":[{"type":7,"id":33790,"data":[0,0,0,1,1,1,0,0,0,1]},{"type":11,"id":34418,"data":[12,34730]},{"type":13,"id":31908,"data":[null,null,1,14,34700,[14,34700],1,1,0,0,-1,-1,1,1,0,0,1,1]}],"children":[],"data":["polySurface468",0,1,0,0]},{"id":33824,"path":"Assets\/Scenes\/Assets\/Prefabs\/howitzer.fbx","assetBundleId":-1,"components":[{"type":7,"id":33792,"data":[0,0,0,1,1,1,0,0,0,1]},{"type":11,"id":34106,"data":[12,34798]},{"type":13,"id":31798,"data":[null,null,1,14,34636,[14,34636],1,1,0,0,-1,-1,1,1,0,0,1,1]}],"children":[],"data":["polySurface469",0,1,0,0]},{"id":33834,"path":"Assets\/Scenes\/Assets\/Prefabs\/howitzer.fbx","assetBundleId":-1,"components":[{"type":7,"id":33794,"data":[0,0,0,1,1,1,0,0,0,1]},{"type":11,"id":34428,"data":[12,34862]},{"type":13,"id":32150,"data":[null,null,1,14,32128,[14,32128],1,1,0,0,-1,-1,1,1,0,0,1,1]}],"children":[],"data":["polySurface470",0,1,0,0]},{"id":33886,"path":"Assets\/Scenes\/Assets\/Prefabs\/howitzer.fbx","assetBundleId":-1,"components":[{"type":7,"id":33796,"data":[0,0,0,1,1,1,0,0,0,1]},{"type":11,"id":34422,"data":[12,34824]},{"type":13,"id":31970,"data":[null,null,1,14,32128,[14,32128],1,1,0,0,-1,-1,1,1,0,0,1,1]}],"children":[],"data":["polySurface471",0,1,0,0]},{"id":33876,"path":"Assets\/Scenes\/Assets\/Prefabs\/howitzer.fbx","assetBundleId":-1,"components":[{"type":7,"id":33798,"data":[0,0,0,1,1,1,0,0,0,1]},{"type":11,"id":34222,"data":[12,34828]},{"type":13,"id":32122,"data":[null,null,1,14,31700,[14,31700],1,1,0,0,-1,-1,1,1,0,0,1,1]}],"children":[],"data":["polySurface476",0,1,0,0]},{"id":33846,"path":"Assets\/Scenes\/Assets\/Prefabs\/howitzer.fbx","assetBundleId":-1,"components":[{"type":7,"id":33800,"data":[0,0,0,1,1,1,0,0,0,1]},{"type":11,"id":34374,"data":[12,35018]},{"type":13,"id":32056,"data":[null,null,1,14,31624,[14,31624],1,1,0,0,-1,-1,1,1,0,0,1,1]}],"children":[],"data":["polySurface477",0,1,0,0]},{"id":33864,"path":"Assets\/Scenes\/Assets\/Prefabs\/howitzer.fbx","assetBundleId":-1,"components":[{"type":7,"id":33802,"data":[0,0,0,1,1,1,0,0,0,1]},{"type":11,"id":34176,"data":[12,34788]},{"type":13,"id":31680,"data":[null,null,1,14,31700,[14,31700],1,1,0,0,-1,-1,1,1,0,0,1,1]}],"children":[],"data":["polySurface478",0,1,0,0]},{"id":32652,"path":"Assets\/Scenes\/Assets\/Prefabs\/howitzer.fbx","assetBundleId":-1,"components":[{"type":7,"id":33804,"data":[0,0,0,1,1,1,0,0,0,1]},{"type":11,"id":34274,"data":[12,34464]},{"type":13,"id":31752,"data":[null,null,1,14,31624,[14,31624],1,1,0,0,-1,-1,1,1,0,0,1,1]}],"children":[],"data":["polySurface479",0,1,0,0]},{"id":33852,"path":"Assets\/Scenes\/Assets\/Prefabs\/howitzer.fbx","assetBundleId":-1,"components":[{"type":7,"id":33806,"data":[0,0,0,1,1,1,0,0,0,1]},{"type":11,"id":34032,"data":[12,34542]},{"type":13,"id":31944,"data":[null,null,1,14,34748,[14,34748],1,1,0,0,-1,-1,1,1,0,0,1,1]}],"children":[],"data":["polySurface488",0,1,0,0]},{"id":33892,"path":"Assets\/Scenes\/Assets\/Prefabs\/howitzer.fbx","assetBundleId":-1,"components":[{"type":7,"id":33808,"data":[0,0,0,1,1,1,0,0,0,1]},{"type":11,"id":34096,"data":[12,34590]},{"type":13,"id":31780,"data":[null,null,1,14,32046,[14,32046],1,1,0,0,-1,-1,1,1,0,0,1,1]}],"children":[],"data":["polySurface489",0,1,0,0]},{"id":32634,"path":"Assets\/Scenes\/Assets\/Prefabs\/howitzer.fbx","assetBundleId":-1,"components":[{"type":7,"id":33810,"data":[0,0,0,1,1,1,0,0,0,1]},{"type":11,"id":34218,"data":[12,34512]},{"type":13,"id":31714,"data":[null,null,1,14,34472,[14,34472],1,1,0,0,-1,-1,1,1,0,0,1,1]}],"children":[],"data":["polySurface495",0,1,0,0]},{"id":32636,"path":"Assets\/Scenes\/Assets\/Prefabs\/howitzer.fbx","assetBundleId":-1,"components":[{"type":7,"id":33812,"data":[0,0,0,1,1,1,0,0,0,1]},{"type":11,"id":34238,"data":[12,34480]},{"type":13,"id":31754,"data":[null,null,1,14,34472,[14,34472],1,1,0,0,-1,-1,1,1,0,0,1,1]}],"children":[],"data":["polySurface496",0,1,0,0]},{"id":32638,"path":"Assets\/Scenes\/Assets\/Prefabs\/howitzer.fbx","assetBundleId":-1,"components":[{"type":7,"id":33814,"data":[0,0,0,1,1,1,0,0,0,1]},{"type":11,"id":34130,"data":[12,34598]},{"type":13,"id":31938,"data":[null,null,1,14,34472,[14,34472],1,1,0,0,-1,-1,1,1,0,0,1,1]}],"children":[],"data":["polySurface497",0,1,0,0]},{"id":32640,"path":"Assets\/Scenes\/Assets\/Prefabs\/howitzer.fbx","assetBundleId":-1,"components":[{"type":7,"id":33816,"data":[0,0,0,1,1,1,0,0,0,1]},{"type":11,"id":34124,"data":[12,34794]},{"type":13,"id":31974,"data":[null,null,1,14,34472,[14,34472],1,1,0,0,-1,-1,1,1,0,0,1,1]}],"children":[],"data":["polySurface498",0,1,0,0]},{"id":33826,"path":"Assets\/Scenes\/Assets\/Prefabs\/howitzer.fbx","assetBundleId":-1,"components":[{"type":7,"id":33818,"data":[0,0,0,1,1,1,0,0,0,1]},{"type":11,"id":34256,"data":[12,34640]},{"type":13,"id":31976,"data":[null,null,1,14,31624,[14,31624],1,1,0,0,-1,-1,1,1,0,0,1,1]}],"children":[],"data":["polySurface499",0,1,0,0]},{"id":33906,"path":"Assets\/Scenes\/Assets\/Prefabs\/howitzer.fbx","assetBundleId":-1,"components":[{"type":7,"id":33820,"data":[0,0,0,1,1,1,0,0,0,1]},{"type":11,"id":34050,"data":[12,34544]},{"type":13,"id":32126,"data":[null,null,1,14,34856,[14,34856],1,1,0,0,-1,-1,1,1,0,0,1,1]}],"children":[],"data":["pPipe1",0,1,0,0]}],"data":["howitzer",0,1,0,0]}